{"id": 9, "name": "1996", "url": "/api/v1/seasons/9", "discipline_kinds": [[0, "lead"], [1, "speed"], [2, "boulder"], [3, "combined"]], "leagues": "World Cups and World Championships", "events": {" 1": {"id": 152, "name": "UIAA Worldcup - Ekaterinburg 1996", "league_id": 1, "league_season_id": 100, "season_id": 9, "starts_at": "1996-09-18 00:00:00 UTC", "ends_at": "1996-09-19 00:00:00 UTC", "local_start_date": "1996-09-18", "local_end_date": "1996-09-19", "timezone": null, "location": "W-Ekaterinburg", "public_information": {"organiser_name": null, "organiser_url": null, "venue_name": null}, "computed_combined_categories": [], "team_ranking_disciplines": ["lead"], "team_ranking_url": "/api/v1/events/152/team_results/", "categories": ["LEAD Men", "LEAD Women"], "results": {"LEAD Men": [{"athlete_id": 4464, "rank": 1, "firstname": "Fran\u00e7ois", "lastname": "Petit", "paraclimbing_sport_class": null, "sport_class_status": null, "country": "FRA", "federation_id": 10, "rounds": []}, {"athlete_id": 847, "rank": 2, "firstname": "Luca", "lastname": "Zardini", "paraclimbing_sport_class": null, "sport_class_status": null, "country": "ITA", "federation_id": 13, "rounds": []}, {"athlete_id": 4472, "rank": 3, "firstname": "Cristian", "lastname": "Brenna", "paraclimbing_sport_class": null, "sport_class_status": null, "country": "ITA", "federation_id": 13, "rounds": []}, {"athlete_id": 392, "rank": 4, "firstname": "Arnaud", "lastname": "Petit", "paraclimbing_sport_class": null, "sport_class_status": null, "country": "FRA", "federation_id": 10, "rounds": []}, {"athlete_id": 4465, "rank": 5, "firstname": "Salavat", "lastname": "Rakhmetov", "paraclimbing_sport_class": null, "sport_class_status": null, "country": "RUS", "federation_id": 7, "rounds": []}, {"athlete_id": 4593, "rank": 6, "firstname": "Fran\u00e7ois", "lastname": "Legrand", "paraclimbing_sport_class": null, "sport_class_status": null, "country": "FRA", "federation_id": 10, "rounds": []}, {"athlete_id": 6488, "rank": 7, "firstname": "Elie", "lastname": "Chevieux", "paraclimbing_sport_class": null, "sport_class_status": null, "country": "SUI", "federation_id": 8, "rounds": []}, {"athlete_id": 4578, "rank": 8, "firstname": "Paul", "lastname": "Dewilde", "paraclimbing_sport_class": null, "sport_class_status": null, "country": "FRA", "federation_id": 10, "rounds": []}, {"athlete_id": 6902, "rank": 9, "firstname": "Serguei", "lastname": "Chemoulinkine", "paraclimbing_sport_class": null, "sport_class_status": null, "country": "RUS", "federation_id": 7, "rounds": []}, {"athlete_id": 843, "rank": 9, "firstname": "Alberto", "lastname": "Gnerro", "paraclimbing_sport_class": null, "sport_class_status": null, "country": "ITA", "federation_id": 13, "rounds": []}, {"athlete_id": 4602, "rank": 9, "firstname": "Aljosa", "lastname": "Grom", "paraclimbing_sport_class": null, "sport_class_status": null, "country": "SLO", "federation_id": 15, "rounds": []}, {"athlete_id": 426, "rank": 9, "firstname": "Sylvain", "lastname": "Millet", "paraclimbing_sport_class": null, "sport_class_status": null, "country": "FRA", "federation_id": 10, "rounds": []}, {"athlete_id": 6558, "rank": 13, "firstname": "Stefano", "lastname": "Alippi", "paraclimbing_sport_class": null, "sport_class_status": null, "country": "ITA", "federation_id": 13, "rounds": []}, {"athlete_id": 6834, "rank": 14, "firstname": "Pascal", "lastname": "Gisler", "paraclimbing_sport_class": null, "sport_class_status": null, "country": "SUI", "federation_id": 8, "rounds": []}, {"athlete_id": 4580, "rank": 15, "firstname": "David", "lastname": "Caude", "paraclimbing_sport_class": null, "sport_class_status": null, "country": "FRA", "federation_id": 10, "rounds": []}, {"athlete_id": 402, "rank": 15, "firstname": "Daniel", "lastname": "DU LAC", "paraclimbing_sport_class": null, "sport_class_status": null, "country": "FRA", "federation_id": 10, "rounds": []}, {"athlete_id": 1467, "rank": 15, "firstname": "Serik", "lastname": "Kazbekov", "paraclimbing_sport_class": null, "sport_class_status": null, "country": "UKR", "federation_id": 18, "rounds": []}, {"athlete_id": 4462, "rank": 18, "firstname": "Pedro", "lastname": "Pons", "paraclimbing_sport_class": null, "sport_class_status": null, "country": "ESP", "federation_id": 12, "rounds": []}, {"athlete_id": 4576, "rank": 19, "firstname": "Yevgen", "lastname": "Kryvosheytsev", "paraclimbing_sport_class": null, "sport_class_status": null, "country": "UKR", "federation_id": 18, "rounds": []}, {"athlete_id": 6560, "rank": 20, "firstname": "Pavel", "lastname": "Samoiline", "paraclimbing_sport_class": null, "sport_class_status": null, "country": "RUS", "federation_id": 7, "rounds": []}, {"athlete_id": 4577, "rank": 21, "firstname": "Simon", "lastname": "Fasnacht Wandeler", "paraclimbing_sport_class": null, "sport_class_status": null, "country": "SUI", "federation_id": 8, "rounds": []}, {"athlete_id": 6623, "rank": 22, "firstname": "Christoph", "lastname": "Finkel", "paraclimbing_sport_class": null, "sport_class_status": null, "country": "GER", "federation_id": 6, "rounds": []}, {"athlete_id": 36, "rank": 23, "firstname": "Dmitrii", "lastname": "Bychkov", "paraclimbing_sport_class": null, "sport_class_status": null, "country": "RUS", "federation_id": 7, "rounds": []}, {"athlete_id": 6883, "rank": 23, "firstname": "David", "lastname": "Carretero Perez", "paraclimbing_sport_class": null, "sport_class_status": null, "country": "ESP", "federation_id": 12, "rounds": []}, {"athlete_id": 6594, "rank": 23, "firstname": "Kairat", "lastname": "Rakhmetov", "paraclimbing_sport_class": null, "sport_class_status": null, "country": "KAZ", "federation_id": 47, "rounds": []}, {"athlete_id": 4584, "rank": 26, "firstname": "Igor", "lastname": "Gusak", "paraclimbing_sport_class": null, "sport_class_status": null, "country": "UKR", "federation_id": 18, "rounds": []}, {"athlete_id": 6893, "rank": 27, "firstname": "Neil", "lastname": "Carson", "paraclimbing_sport_class": null, "sport_class_status": null, "country": "GBR", "federation_id": 11, "rounds": []}, {"athlete_id": 6766, "rank": 28, "firstname": "David", "lastname": "Villien", "paraclimbing_sport_class": null, "sport_class_status": null, "country": "FRA", "federation_id": 10, "rounds": []}, {"athlete_id": 4468, "rank": 29, "firstname": "Mathieu", "lastname": "Dutray", "paraclimbing_sport_class": null, "sport_class_status": null, "country": "FRA", "federation_id": 10, "rounds": []}, {"athlete_id": 6497, "rank": 29, "firstname": "Vili", "lastname": "Gucek", "paraclimbing_sport_class": null, "sport_class_status": null, "country": "SLO", "federation_id": 15, "rounds": []}, {"athlete_id": 4467, "rank": 31, "firstname": "Daniel", "lastname": "ANDRADA JIMENEZ", "paraclimbing_sport_class": null, "sport_class_status": null, "country": "ESP", "federation_id": 12, "rounds": []}, {"athlete_id": 1466, "rank": 31, "firstname": "Andrey", "lastname": "Vedenmeer", "paraclimbing_sport_class": null, "sport_class_status": null, "country": "UKR", "federation_id": 18, "rounds": []}, {"athlete_id": 6946, "rank": 33, "firstname": "Oleg", "lastname": "Boulavko", "paraclimbing_sport_class": null, "sport_class_status": null, "country": "RUS", "federation_id": 7, "rounds": []}, {"athlete_id": 628, "rank": 33, "firstname": "Barry", "lastname": "Durston", "paraclimbing_sport_class": null, "sport_class_status": null, "country": "GBR", "federation_id": 11, "rounds": []}, {"athlete_id": 32, "rank": 33, "firstname": "Alexei", "lastname": "Shalygin", "paraclimbing_sport_class": null, "sport_class_status": null, "country": "RUS", "federation_id": 7, "rounds": []}, {"athlete_id": 6476, "rank": 33, "firstname": "Alexei", "lastname": "Tchertov", "paraclimbing_sport_class": null, "sport_class_status": null, "country": "RUS", "federation_id": 7, "rounds": []}, {"athlete_id": 4597, "rank": 37, "firstname": "Andreas", "lastname": "Bindhammer", "paraclimbing_sport_class": null, "sport_class_status": null, "country": "GER", "federation_id": 6, "rounds": []}, {"athlete_id": 4586, "rank": 37, "firstname": "Christian", "lastname": "Bindhammer", "paraclimbing_sport_class": null, "sport_class_status": null, "country": "GER", "federation_id": 6, "rounds": []}, {"athlete_id": 4618, "rank": 37, "firstname": "Serguei", "lastname": "Nourmamatov", "paraclimbing_sport_class": null, "sport_class_status": null, "country": "RUS", "federation_id": 7, "rounds": []}, {"athlete_id": 1465, "rank": 37, "firstname": "Alexandr", "lastname": "Paukaev", "paraclimbing_sport_class": null, "sport_class_status": null, "country": "UKR", "federation_id": 18, "rounds": []}, {"athlete_id": 6991, "rank": 41, "firstname": "Byung Tae", "lastname": "Kim", "paraclimbing_sport_class": null, "sport_class_status": null, "country": "KOR", "federation_id": 21, "rounds": []}, {"athlete_id": 6860, "rank": 42, "firstname": "Maxim", "lastname": "Kozlov", "paraclimbing_sport_class": null, "sport_class_status": null, "country": "RUS", "federation_id": 7, "rounds": []}, {"athlete_id": 4734, "rank": 43, "firstname": "Kyu-Bog", "lastname": "Cho", "paraclimbing_sport_class": null, "sport_class_status": null, "country": "KOR", "federation_id": 21, "rounds": []}, {"athlete_id": 5056, "rank": 43, "firstname": "Hee-Jo", "lastname": "Kim", "paraclimbing_sport_class": null, "sport_class_status": null, "country": "KOR", "federation_id": 21, "rounds": []}, {"athlete_id": 6960, "rank": 45, "firstname": "Pavel", "lastname": "Demin", "paraclimbing_sport_class": null, "sport_class_status": null, "country": "RUS", "federation_id": 7, "rounds": []}, {"athlete_id": 5162, "rank": 45, "firstname": "Ilfir", "lastname": "Khakimianov", "paraclimbing_sport_class": null, "sport_class_status": null, "country": "RUS", "federation_id": 7, "rounds": []}, {"athlete_id": 5076, "rank": 47, "firstname": "Christopher", "lastname": "Cubitt", "paraclimbing_sport_class": null, "sport_class_status": null, "country": "GBR", "federation_id": 11, "rounds": []}, {"athlete_id": 4581, "rank": 47, "firstname": "Tomasz", "lastname": "Oleksy", "paraclimbing_sport_class": null, "sport_class_status": null, "country": "POL", "federation_id": 36, "rounds": []}, {"athlete_id": 6961, "rank": 47, "firstname": "Evgeni", "lastname": "Zvonnarev", "paraclimbing_sport_class": null, "sport_class_status": null, "country": "KAZ", "federation_id": 47, "rounds": []}, {"athlete_id": 6964, "rank": 50, "firstname": "Serguei", "lastname": "Chichkine", "paraclimbing_sport_class": null, "sport_class_status": null, "country": "KAZ", "federation_id": 47, "rounds": []}], "LEAD Women": [{"athlete_id": 4530, "rank": 1, "firstname": "Liv", "lastname": "Sansoz", "paraclimbing_sport_class": null, "sport_class_status": null, "country": "FRA", "federation_id": 10, "rounds": []}, {"athlete_id": 6728, "rank": 2, "firstname": "Laurence", "lastname": "Guyon", "paraclimbing_sport_class": null, "sport_class_status": null, "country": "FRA", "federation_id": 10, "rounds": []}, {"athlete_id": 4449, "rank": 3, "firstname": "Elena", "lastname": "Choumilova", "paraclimbing_sport_class": null, "sport_class_status": null, "country": "RUS", "federation_id": 7, "rounds": []}, {"athlete_id": 4529, "rank": 4, "firstname": "St\u00e9phanie", "lastname": "Bodet", "paraclimbing_sport_class": null, "sport_class_status": null, "country": "FRA", "federation_id": 10, "rounds": []}, {"athlete_id": 427, "rank": 5, "firstname": "Cecile", "lastname": "Avezou", "paraclimbing_sport_class": null, "sport_class_status": null, "country": "FRA", "federation_id": 10, "rounds": []}, {"athlete_id": 6727, "rank": 6, "firstname": "Marie", "lastname": "Guillet", "paraclimbing_sport_class": null, "sport_class_status": null, "country": "FRA", "federation_id": 10, "rounds": []}, {"athlete_id": 4720, "rank": 7, "firstname": "Marietta", "lastname": "Uhden", "paraclimbing_sport_class": null, "sport_class_status": null, "country": "GER", "federation_id": 6, "rounds": []}, {"athlete_id": 6533, "rank": 8, "firstname": "Natalie", "lastname": "Richer", "paraclimbing_sport_class": null, "sport_class_status": null, "country": "FRA", "federation_id": 10, "rounds": []}, {"athlete_id": 4565, "rank": 9, "firstname": "Zosia", "lastname": "Podgorbounskikh", "paraclimbing_sport_class": null, "sport_class_status": null, "country": "RUS", "federation_id": 7, "rounds": []}, {"athlete_id": 6916, "rank": 10, "firstname": "Galina", "lastname": "Agapova", "paraclimbing_sport_class": null, "sport_class_status": null, "country": "RUS", "federation_id": 7, "rounds": []}, {"athlete_id": 4486, "rank": 11, "firstname": "Martina", "lastname": "Cufar", "paraclimbing_sport_class": null, "sport_class_status": null, "country": "SLO", "federation_id": 15, "rounds": []}, {"athlete_id": 5109, "rank": 12, "firstname": "Venera", "lastname": "Chereshneva", "paraclimbing_sport_class": null, "sport_class_status": null, "country": "RUS", "federation_id": 7, "rounds": []}, {"athlete_id": 4540, "rank": 13, "firstname": "Elena", "lastname": "Ovtchinnikova", "paraclimbing_sport_class": null, "sport_class_status": null, "country": "USA", "federation_id": 20, "rounds": []}, {"athlete_id": 4719, "rank": 14, "firstname": "Mi-Sun", "lastname": "Go", "paraclimbing_sport_class": null, "sport_class_status": null, "country": "KOR", "federation_id": 21, "rounds": []}, {"athlete_id": 6866, "rank": 15, "firstname": "Mia", "lastname": "Axon", "paraclimbing_sport_class": null, "sport_class_status": null, "country": "USA", "federation_id": 20, "rounds": []}, {"athlete_id": 4536, "rank": 16, "firstname": "Josune", "lastname": "Bereciartu Urruzola", "paraclimbing_sport_class": null, "sport_class_status": null, "country": "ESP", "federation_id": 12, "rounds": []}, {"athlete_id": 42, "rank": 17, "firstname": "Tatiana", "lastname": "Ruyga", "paraclimbing_sport_class": null, "sport_class_status": null, "country": "RUS", "federation_id": 7, "rounds": []}, {"athlete_id": 5114, "rank": 17, "firstname": "Svetlana", "lastname": "Sutkina", "paraclimbing_sport_class": null, "sport_class_status": null, "country": "RUS", "federation_id": 7, "rounds": []}, {"athlete_id": 4532, "rank": 19, "firstname": "Renata", "lastname": "Piszczek", "paraclimbing_sport_class": null, "sport_class_status": null, "country": "POL", "federation_id": 36, "rounds": []}, {"athlete_id": 6992, "rank": 20, "firstname": "Katarina", "lastname": "Stremfelj", "paraclimbing_sport_class": null, "sport_class_status": null, "country": "SLO", "federation_id": 15, "rounds": []}, {"athlete_id": 4546, "rank": 21, "firstname": "Irina", "lastname": "Rouiga", "paraclimbing_sport_class": null, "sport_class_status": null, "country": "RUS", "federation_id": 7, "rounds": []}, {"athlete_id": 4455, "rank": 22, "firstname": "Chlo\u00e9", "lastname": "Minoret", "paraclimbing_sport_class": null, "sport_class_status": null, "country": "FRA", "federation_id": 10, "rounds": []}, {"athlete_id": 41, "rank": 23, "firstname": "Olga", "lastname": "Bibik", "paraclimbing_sport_class": null, "sport_class_status": null, "country": "RUS", "federation_id": 7, "rounds": []}, {"athlete_id": 4571, "rank": 24, "firstname": "Natalia", "lastname": "Minaeva", "paraclimbing_sport_class": null, "sport_class_status": null, "country": "RUS", "federation_id": 7, "rounds": []}, {"athlete_id": 39, "rank": 24, "firstname": "Mayya", "lastname": "Piratinskaya", "paraclimbing_sport_class": null, "sport_class_status": null, "country": "RUS", "federation_id": 7, "rounds": []}, {"athlete_id": 6546, "rank": 24, "firstname": "Tamara", "lastname": "Schlemmer", "paraclimbing_sport_class": null, "sport_class_status": null, "country": "GER", "federation_id": 6, "rounds": []}, {"athlete_id": 5364, "rank": 27, "firstname": "Karin", "lastname": "Magog", "paraclimbing_sport_class": null, "sport_class_status": null, "country": "GBR", "federation_id": 11, "rounds": []}, {"athlete_id": 4555, "rank": 28, "firstname": "Anne", "lastname": "Arran", "paraclimbing_sport_class": null, "sport_class_status": null, "country": "GBR", "federation_id": 11, "rounds": []}, {"athlete_id": 6545, "rank": 28, "firstname": "Metka", "lastname": "Lukancic", "paraclimbing_sport_class": null, "sport_class_status": null, "country": "SLO", "federation_id": 15, "rounds": []}, {"athlete_id": 1468, "rank": 30, "firstname": "Olena", "lastname": "Ryepko", "paraclimbing_sport_class": null, "sport_class_status": null, "country": "UKR", "federation_id": 18, "rounds": []}, {"athlete_id": 4573, "rank": 30, "firstname": "Olga", "lastname": "Zakharova", "paraclimbing_sport_class": null, "sport_class_status": null, "country": "UKR", "federation_id": 18, "rounds": []}, {"athlete_id": 4702, "rank": 32, "firstname": "Olena", "lastname": "Ostapenko", "paraclimbing_sport_class": null, "sport_class_status": null, "country": "UKR", "federation_id": 18, "rounds": []}, {"athlete_id": 4721, "rank": 33, "firstname": "Hyun-Jung", "lastname": "Kim", "paraclimbing_sport_class": null, "sport_class_status": null, "country": "KOR", "federation_id": 21, "rounds": []}, {"athlete_id": 6993, "rank": 34, "firstname": "Maria", "lastname": "Jarokh", "paraclimbing_sport_class": null, "sport_class_status": null, "country": "UKR", "federation_id": 18, "rounds": []}, {"athlete_id": 5157, "rank": 35, "firstname": "Natalia", "lastname": "Nesterova", "paraclimbing_sport_class": null, "sport_class_status": null, "country": "RUS", "federation_id": 7, "rounds": []}, {"athlete_id": 6994, "rank": 36, "firstname": "Galina", "lastname": "Chichkina", "paraclimbing_sport_class": null, "sport_class_status": null, "country": "KAZ", "federation_id": 47, "rounds": []}, {"athlete_id": 6995, "rank": 37, "firstname": "Kyung-Soo", "lastname": "Yang", "paraclimbing_sport_class": null, "sport_class_status": null, "country": "KOR", "federation_id": 21, "rounds": []}]}}, " 2": {"id": 153, "name": "UIAA Worldcup - Kranj 1996", "league_id": 1, "league_season_id": 100, "season_id": 9, "starts_at": "1996-11-23 00:00:00 UTC", "ends_at": "1996-11-24 00:00:00 UTC", "local_start_date": "1996-11-23", "local_end_date": "1996-11-24", "timezone": null, "location": "W-Kranj", "public_information": {"organiser_name": null, "organiser_url": null, "venue_name": null}, "computed_combined_categories": [], "team_ranking_disciplines": ["lead"], "team_ranking_url": "/api/v1/events/153/team_results/", "categories": ["LEAD Men", "LEAD Women"], "results": {"LEAD Men": [{"athlete_id": 392, "rank": 1, "firstname": "Arnaud", "lastname": "Petit", "paraclimbing_sport_class": null, "sport_class_status": null, "country": "FRA", "federation_id": 10, "rounds": []}, {"athlete_id": 4464, "rank": 2, "firstname": "Fran\u00e7ois", "lastname": "Petit", "paraclimbing_sport_class": null, "sport_class_status": null, "country": "FRA", "federation_id": 10, "rounds": []}, {"athlete_id": 4580, "rank": 3, "firstname": "David", "lastname": "Caude", "paraclimbing_sport_class": null, "sport_class_status": null, "country": "FRA", "federation_id": 10, "rounds": []}, {"athlete_id": 4472, "rank": 4, "firstname": "Cristian", "lastname": "Brenna", "paraclimbing_sport_class": null, "sport_class_status": null, "country": "ITA", "federation_id": 13, "rounds": []}, {"athlete_id": 4593, "rank": 5, "firstname": "Fran\u00e7ois", "lastname": "Legrand", "paraclimbing_sport_class": null, "sport_class_status": null, "country": "FRA", "federation_id": 10, "rounds": []}, {"athlete_id": 2247, "rank": 6, "firstname": "Yuji", "lastname": "Hirayama", "paraclimbing_sport_class": null, "sport_class_status": null, "country": "JPN", "federation_id": 25, "rounds": []}, {"athlete_id": 847, "rank": 7, "firstname": "Luca", "lastname": "Zardini", "paraclimbing_sport_class": null, "sport_class_status": null, "country": "ITA", "federation_id": 13, "rounds": []}, {"athlete_id": 4586, "rank": 8, "firstname": "Christian", "lastname": "Bindhammer", "paraclimbing_sport_class": null, "sport_class_status": null, "country": "GER", "federation_id": 6, "rounds": []}, {"athlete_id": 843, "rank": 9, "firstname": "Alberto", "lastname": "Gnerro", "paraclimbing_sport_class": null, "sport_class_status": null, "country": "ITA", "federation_id": 13, "rounds": []}, {"athlete_id": 6902, "rank": 10, "firstname": "Serguei", "lastname": "Chemoulinkine", "paraclimbing_sport_class": null, "sport_class_status": null, "country": "RUS", "federation_id": 7, "rounds": []}, {"athlete_id": 4463, "rank": 11, "firstname": "Christian", "lastname": "Core", "paraclimbing_sport_class": null, "sport_class_status": null, "country": "ITA", "federation_id": 13, "rounds": []}, {"athlete_id": 4462, "rank": 12, "firstname": "Pedro", "lastname": "Pons", "paraclimbing_sport_class": null, "sport_class_status": null, "country": "ESP", "federation_id": 12, "rounds": []}, {"athlete_id": 5435, "rank": 12, "firstname": "Frederic", "lastname": "Sarkany", "paraclimbing_sport_class": null, "sport_class_status": null, "country": "BEL", "federation_id": 9, "rounds": []}, {"athlete_id": 1115, "rank": 14, "firstname": "Jurij", "lastname": "Golob", "paraclimbing_sport_class": null, "sport_class_status": null, "country": "SLO", "federation_id": 15, "rounds": []}, {"athlete_id": 4578, "rank": 15, "firstname": "Paul", "lastname": "Dewilde", "paraclimbing_sport_class": null, "sport_class_status": null, "country": "FRA", "federation_id": 10, "rounds": []}, {"athlete_id": 4576, "rank": 15, "firstname": "Yevgen", "lastname": "Kryvosheytsev", "paraclimbing_sport_class": null, "sport_class_status": null, "country": "UKR", "federation_id": 18, "rounds": []}, {"athlete_id": 6488, "rank": 17, "firstname": "Elie", "lastname": "Chevieux", "paraclimbing_sport_class": null, "sport_class_status": null, "country": "SUI", "federation_id": 8, "rounds": []}, {"athlete_id": 6623, "rank": 17, "firstname": "Christoph", "lastname": "Finkel", "paraclimbing_sport_class": null, "sport_class_status": null, "country": "GER", "federation_id": 6, "rounds": []}, {"athlete_id": 4465, "rank": 17, "firstname": "Salavat", "lastname": "Rakhmetov", "paraclimbing_sport_class": null, "sport_class_status": null, "country": "RUS", "federation_id": 7, "rounds": []}, {"athlete_id": 6766, "rank": 20, "firstname": "David", "lastname": "Villien", "paraclimbing_sport_class": null, "sport_class_status": null, "country": "FRA", "federation_id": 10, "rounds": []}, {"athlete_id": 5047, "rank": 21, "firstname": "Mauro", "lastname": "Calibani", "paraclimbing_sport_class": null, "sport_class_status": null, "country": "ITA", "federation_id": 13, "rounds": []}, {"athlete_id": 6497, "rank": 22, "firstname": "Vili", "lastname": "Gucek", "paraclimbing_sport_class": null, "sport_class_status": null, "country": "SLO", "federation_id": 15, "rounds": []}, {"athlete_id": 6558, "rank": 23, "firstname": "Stefano", "lastname": "Alippi", "paraclimbing_sport_class": null, "sport_class_status": null, "country": "ITA", "federation_id": 13, "rounds": []}, {"athlete_id": 6594, "rank": 23, "firstname": "Kairat", "lastname": "Rakhmetov", "paraclimbing_sport_class": null, "sport_class_status": null, "country": "KAZ", "federation_id": 47, "rounds": []}, {"athlete_id": 6476, "rank": 23, "firstname": "Alexei", "lastname": "Tchertov", "paraclimbing_sport_class": null, "sport_class_status": null, "country": "RUS", "federation_id": 7, "rounds": []}, {"athlete_id": 4713, "rank": 26, "firstname": "Franci", "lastname": "Jensterle", "paraclimbing_sport_class": null, "sport_class_status": null, "country": "SLO", "federation_id": 15, "rounds": []}, {"athlete_id": 4477, "rank": 27, "firstname": "Timmy", "lastname": "Fairfield", "paraclimbing_sport_class": null, "sport_class_status": null, "country": "CAN", "federation_id": 19, "rounds": []}, {"athlete_id": 846, "rank": 27, "firstname": "Luca", "lastname": "Giupponi", "paraclimbing_sport_class": null, "sport_class_status": null, "country": "ITA", "federation_id": 13, "rounds": []}, {"athlete_id": 4618, "rank": 27, "firstname": "Serguei", "lastname": "Nourmamatov", "paraclimbing_sport_class": null, "sport_class_status": null, "country": "RUS", "federation_id": 7, "rounds": []}, {"athlete_id": 6893, "rank": 30, "firstname": "Neil", "lastname": "Carson", "paraclimbing_sport_class": null, "sport_class_status": null, "country": "GBR", "federation_id": 11, "rounds": []}, {"athlete_id": 6996, "rank": 31, "firstname": "Massimo", "lastname": "Bruseghini", "paraclimbing_sport_class": null, "sport_class_status": null, "country": "ITA", "federation_id": 13, "rounds": []}, {"athlete_id": 2752, "rank": 31, "firstname": "Andrej", "lastname": "Chrastina", "paraclimbing_sport_class": null, "sport_class_status": null, "country": "SVK", "federation_id": 34, "rounds": []}, {"athlete_id": 420, "rank": 31, "firstname": "Mathieu", "lastname": "Gallot-Lavallee", "paraclimbing_sport_class": null, "sport_class_status": null, "country": "FRA", "federation_id": 10, "rounds": []}, {"athlete_id": 426, "rank": 31, "firstname": "Sylvain", "lastname": "Millet", "paraclimbing_sport_class": null, "sport_class_status": null, "country": "FRA", "federation_id": 10, "rounds": []}, {"athlete_id": 4577, "rank": 31, "firstname": "Simon", "lastname": "Fasnacht Wandeler", "paraclimbing_sport_class": null, "sport_class_status": null, "country": "SUI", "federation_id": 8, "rounds": []}, {"athlete_id": 844, "rank": 36, "firstname": "Donato", "lastname": "Lella", "paraclimbing_sport_class": null, "sport_class_status": null, "country": "ITA", "federation_id": 13, "rounds": []}, {"athlete_id": 4467, "rank": 37, "firstname": "Daniel", "lastname": "ANDRADA JIMENEZ", "paraclimbing_sport_class": null, "sport_class_status": null, "country": "ESP", "federation_id": 12, "rounds": []}, {"athlete_id": 6836, "rank": 37, "firstname": "Milan", "lastname": "Benian", "paraclimbing_sport_class": null, "sport_class_status": null, "country": "CZE", "federation_id": 17, "rounds": []}, {"athlete_id": 4597, "rank": 37, "firstname": "Andreas", "lastname": "Bindhammer", "paraclimbing_sport_class": null, "sport_class_status": null, "country": "GER", "federation_id": 6, "rounds": []}, {"athlete_id": 6883, "rank": 37, "firstname": "David", "lastname": "Carretero Perez", "paraclimbing_sport_class": null, "sport_class_status": null, "country": "ESP", "federation_id": 12, "rounds": []}, {"athlete_id": 5076, "rank": 41, "firstname": "Christopher", "lastname": "Cubitt", "paraclimbing_sport_class": null, "sport_class_status": null, "country": "GBR", "federation_id": 11, "rounds": []}, {"athlete_id": 402, "rank": 42, "firstname": "Daniel", "lastname": "DU LAC", "paraclimbing_sport_class": null, "sport_class_status": null, "country": "FRA", "federation_id": 10, "rounds": []}, {"athlete_id": 6927, "rank": 43, "firstname": "Peter", "lastname": "Kmosko", "paraclimbing_sport_class": null, "sport_class_status": null, "country": "SVK", "federation_id": 34, "rounds": []}, {"athlete_id": 6499, "rank": 43, "firstname": "Marko", "lastname": "Lukic", "paraclimbing_sport_class": null, "sport_class_status": null, "country": "SLO", "federation_id": 15, "rounds": []}, {"athlete_id": 6997, "rank": 45, "firstname": "Jan", "lastname": "Kares", "paraclimbing_sport_class": null, "sport_class_status": null, "country": "CZE", "federation_id": 17, "rounds": []}, {"athlete_id": 2417, "rank": 45, "firstname": "Milen", "lastname": "Videnovski", "paraclimbing_sport_class": null, "sport_class_status": null, "country": "BUL", "federation_id": 26, "rounds": []}, {"athlete_id": 4584, "rank": 47, "firstname": "Igor", "lastname": "Gusak", "paraclimbing_sport_class": null, "sport_class_status": null, "country": "UKR", "federation_id": 18, "rounds": []}, {"athlete_id": 4588, "rank": 47, "firstname": "Marek", "lastname": "Havlik", "paraclimbing_sport_class": null, "sport_class_status": null, "country": "CZE", "federation_id": 17, "rounds": []}, {"athlete_id": 6797, "rank": 49, "firstname": "Michael", "lastname": "Lea", "paraclimbing_sport_class": null, "sport_class_status": null, "country": "GBR", "federation_id": 11, "rounds": []}, {"athlete_id": 2827, "rank": 49, "firstname": "Adam", "lastname": "Liana", "paraclimbing_sport_class": null, "sport_class_status": null, "country": "POL", "federation_id": 36, "rounds": []}, {"athlete_id": 4582, "rank": 49, "firstname": "Matej", "lastname": "Sova", "paraclimbing_sport_class": null, "sport_class_status": null, "country": "SLO", "federation_id": 15, "rounds": []}, {"athlete_id": 5264, "rank": 52, "firstname": "Pavel", "lastname": "Koran", "paraclimbing_sport_class": null, "sport_class_status": null, "country": "CZE", "federation_id": 17, "rounds": []}, {"athlete_id": 6998, "rank": 53, "firstname": "Gyula", "lastname": "Dozsa", "paraclimbing_sport_class": null, "sport_class_status": null, "country": "HUN", "federation_id": 23, "rounds": []}, {"athlete_id": 4594, "rank": 53, "firstname": "Urs", "lastname": "Sch\u00f6nenberger", "paraclimbing_sport_class": null, "sport_class_status": null, "country": "SUI", "federation_id": 8, "rounds": []}, {"athlete_id": 6596, "rank": 55, "firstname": "Christoph", "lastname": "Bucher", "paraclimbing_sport_class": null, "sport_class_status": null, "country": "GER", "federation_id": 6, "rounds": []}, {"athlete_id": 4602, "rank": 55, "firstname": "Aljosa", "lastname": "Grom", "paraclimbing_sport_class": null, "sport_class_status": null, "country": "SLO", "federation_id": 15, "rounds": []}, {"athlete_id": 6999, "rank": 57, "firstname": "Thomas", "lastname": "Feuerstein", "paraclimbing_sport_class": null, "sport_class_status": null, "country": "AUT", "federation_id": 16, "rounds": []}, {"athlete_id": 2416, "rank": 57, "firstname": "Kalin", "lastname": "Garbov", "paraclimbing_sport_class": null, "sport_class_status": null, "country": "BUL", "federation_id": 26, "rounds": []}, {"athlete_id": 2716, "rank": 59, "firstname": "Christian", "lastname": "Simion", "paraclimbing_sport_class": null, "sport_class_status": null, "country": "ROU", "federation_id": 33, "rounds": []}, {"athlete_id": 6950, "rank": 59, "firstname": "Sebastian", "lastname": "Zasadzki", "paraclimbing_sport_class": null, "sport_class_status": null, "country": "POL", "federation_id": 36, "rounds": []}, {"athlete_id": 6962, "rank": 61, "firstname": "Janos", "lastname": "Nagy", "paraclimbing_sport_class": null, "sport_class_status": null, "country": "HUN", "federation_id": 23, "rounds": []}, {"athlete_id": 2753, "rank": 61, "firstname": "Anton", "lastname": "Pacek", "paraclimbing_sport_class": null, "sport_class_status": null, "country": "SVK", "federation_id": 34, "rounds": []}, {"athlete_id": 3725, "rank": 63, "firstname": "Ben", "lastname": "Ryan", "paraclimbing_sport_class": null, "sport_class_status": null, "country": "NZL", "federation_id": 53, "rounds": []}, {"athlete_id": 7000, "rank": 63, "firstname": "Dan", "lastname": "Scortea", "paraclimbing_sport_class": null, "sport_class_status": null, "country": "ROU", "federation_id": 33, "rounds": []}, {"athlete_id": 6715, "rank": 65, "firstname": "Ionel", "lastname": "Ene", "paraclimbing_sport_class": null, "sport_class_status": null, "country": "ROU", "federation_id": 33, "rounds": []}, {"athlete_id": 2171, "rank": 65, "firstname": "Laszlo", "lastname": "Strommer", "paraclimbing_sport_class": null, "sport_class_status": null, "country": "HUN", "federation_id": 23, "rounds": []}, {"athlete_id": 5128, "rank": 65, "firstname": "Takaaki", "lastname": "Tsuiki", "paraclimbing_sport_class": null, "sport_class_status": null, "country": "JPN", "federation_id": 25, "rounds": []}, {"athlete_id": 7001, "rank": 68, "firstname": "Nikolaos", "lastname": "Theodorou", "paraclimbing_sport_class": null, "sport_class_status": null, "country": "GRE", "federation_id": 64, "rounds": []}, {"athlete_id": 4110, "rank": 69, "firstname": "Aristomenes", "lastname": "Thanopoulos", "paraclimbing_sport_class": null, "sport_class_status": null, "country": "GRE", "federation_id": 64, "rounds": []}, {"athlete_id": 7002, "rank": 69, "firstname": "Ioannis", "lastname": "Tsaousis", "paraclimbing_sport_class": null, "sport_class_status": null, "country": "GRE", "federation_id": 64, "rounds": []}], "LEAD Women": [{"athlete_id": 6728, "rank": 1, "firstname": "Laurence", "lastname": "Guyon", "paraclimbing_sport_class": null, "sport_class_status": null, "country": "FRA", "federation_id": 10, "rounds": []}, {"athlete_id": 306, "rank": 2, "firstname": "Muriel", "lastname": "Sarkany", "paraclimbing_sport_class": null, "sport_class_status": null, "country": "BEL", "federation_id": 9, "rounds": []}, {"athlete_id": 4530, "rank": 3, "firstname": "Liv", "lastname": "Sansoz", "paraclimbing_sport_class": null, "sport_class_status": null, "country": "FRA", "federation_id": 10, "rounds": []}, {"athlete_id": 6533, "rank": 4, "firstname": "Natalie", "lastname": "Richer", "paraclimbing_sport_class": null, "sport_class_status": null, "country": "FRA", "federation_id": 10, "rounds": []}, {"athlete_id": 4529, "rank": 5, "firstname": "St\u00e9phanie", "lastname": "Bodet", "paraclimbing_sport_class": null, "sport_class_status": null, "country": "FRA", "federation_id": 10, "rounds": []}, {"athlete_id": 4486, "rank": 6, "firstname": "Martina", "lastname": "Cufar", "paraclimbing_sport_class": null, "sport_class_status": null, "country": "SLO", "federation_id": 15, "rounds": []}, {"athlete_id": 4720, "rank": 7, "firstname": "Marietta", "lastname": "Uhden", "paraclimbing_sport_class": null, "sport_class_status": null, "country": "GER", "federation_id": 6, "rounds": []}, {"athlete_id": 6727, "rank": 8, "firstname": "Marie", "lastname": "Guillet", "paraclimbing_sport_class": null, "sport_class_status": null, "country": "FRA", "federation_id": 10, "rounds": []}, {"athlete_id": 427, "rank": 9, "firstname": "Cecile", "lastname": "Avezou", "paraclimbing_sport_class": null, "sport_class_status": null, "country": "FRA", "federation_id": 10, "rounds": []}, {"athlete_id": 6545, "rank": 10, "firstname": "Metka", "lastname": "Lukancic", "paraclimbing_sport_class": null, "sport_class_status": null, "country": "SLO", "federation_id": 15, "rounds": []}, {"athlete_id": 4549, "rank": 11, "firstname": "Luisa", "lastname": "Iovane", "paraclimbing_sport_class": null, "sport_class_status": null, "country": "ITA", "federation_id": 13, "rounds": []}, {"athlete_id": 4449, "rank": 12, "firstname": "Elena", "lastname": "Choumilova", "paraclimbing_sport_class": null, "sport_class_status": null, "country": "RUS", "federation_id": 7, "rounds": []}, {"athlete_id": 6992, "rank": 12, "firstname": "Katarina", "lastname": "Stremfelj", "paraclimbing_sport_class": null, "sport_class_status": null, "country": "SLO", "federation_id": 15, "rounds": []}, {"athlete_id": 6866, "rank": 14, "firstname": "Mia", "lastname": "Axon", "paraclimbing_sport_class": null, "sport_class_status": null, "country": "USA", "federation_id": 20, "rounds": []}, {"athlete_id": 6694, "rank": 15, "firstname": "Mirjam", "lastname": "Verbeek", "paraclimbing_sport_class": null, "sport_class_status": null, "country": "NED", "federation_id": 50, "rounds": []}, {"athlete_id": 6978, "rank": 16, "firstname": "Iva", "lastname": "Hartmann", "paraclimbing_sport_class": null, "sport_class_status": null, "country": "SUI", "federation_id": 8, "rounds": []}, {"athlete_id": 4555, "rank": 17, "firstname": "Anne", "lastname": "Arran", "paraclimbing_sport_class": null, "sport_class_status": null, "country": "GBR", "federation_id": 11, "rounds": []}, {"athlete_id": 1203, "rank": 18, "firstname": "Bettina", "lastname": "sch\u00f6pf", "paraclimbing_sport_class": null, "sport_class_status": null, "country": "AUT", "federation_id": 16, "rounds": []}, {"athlete_id": 4452, "rank": 19, "firstname": "Ingela", "lastname": "Nilsson", "paraclimbing_sport_class": null, "sport_class_status": null, "country": "SWE", "federation_id": 32, "rounds": []}, {"athlete_id": 4485, "rank": 20, "firstname": "Kim", "lastname": "Anthoni", "paraclimbing_sport_class": null, "sport_class_status": null, "country": "BEL", "federation_id": 9, "rounds": []}, {"athlete_id": 4455, "rank": 21, "firstname": "Chlo\u00e9", "lastname": "Minoret", "paraclimbing_sport_class": null, "sport_class_status": null, "country": "FRA", "federation_id": 10, "rounds": []}, {"athlete_id": 6895, "rank": 22, "firstname": "Silvia", "lastname": "Pearsons", "paraclimbing_sport_class": null, "sport_class_status": null, "country": "GBR", "federation_id": 11, "rounds": []}, {"athlete_id": 6555, "rank": 23, "firstname": "Catherine", "lastname": "Vallet", "paraclimbing_sport_class": null, "sport_class_status": null, "country": "FRA", "federation_id": 10, "rounds": []}, {"athlete_id": 5197, "rank": 24, "firstname": "Stella", "lastname": "Marchisio", "paraclimbing_sport_class": null, "sport_class_status": null, "country": "ITA", "federation_id": 13, "rounds": []}, {"athlete_id": 7003, "rank": 24, "firstname": "Meryl", "lastname": "Singer", "paraclimbing_sport_class": null, "sport_class_status": null, "country": "USA", "federation_id": 20, "rounds": []}, {"athlete_id": 5114, "rank": 24, "firstname": "Svetlana", "lastname": "Sutkina", "paraclimbing_sport_class": null, "sport_class_status": null, "country": "RUS", "federation_id": 7, "rounds": []}, {"athlete_id": 6916, "rank": 27, "firstname": "Galina", "lastname": "Agapova", "paraclimbing_sport_class": null, "sport_class_status": null, "country": "RUS", "federation_id": 7, "rounds": []}, {"athlete_id": 5096, "rank": 27, "firstname": "Eva", "lastname": "Nieselt", "paraclimbing_sport_class": null, "sport_class_status": null, "country": "GER", "federation_id": 6, "rounds": []}, {"athlete_id": 7004, "rank": 27, "firstname": "Delphine", "lastname": "Pigneur", "paraclimbing_sport_class": null, "sport_class_status": null, "country": "FRA", "federation_id": 10, "rounds": []}, {"athlete_id": 4461, "rank": 27, "firstname": "Romana", "lastname": "Savic", "paraclimbing_sport_class": null, "sport_class_status": null, "country": "SLO", "federation_id": 15, "rounds": []}, {"athlete_id": 7005, "rank": 31, "firstname": "Blaza", "lastname": "Klemencic", "paraclimbing_sport_class": null, "sport_class_status": null, "country": "SLO", "federation_id": 15, "rounds": []}, {"athlete_id": 4532, "rank": 31, "firstname": "Renata", "lastname": "Piszczek", "paraclimbing_sport_class": null, "sport_class_status": null, "country": "POL", "federation_id": 36, "rounds": []}, {"athlete_id": 6530, "rank": 33, "firstname": "Felicity", "lastname": "Butler", "paraclimbing_sport_class": null, "sport_class_status": null, "country": "GBR", "federation_id": 11, "rounds": []}, {"athlete_id": 4538, "rank": 34, "firstname": "Iwona", "lastname": "Gronkiewicz-Marcisz", "paraclimbing_sport_class": null, "sport_class_status": null, "country": "POL", "federation_id": 36, "rounds": []}, {"athlete_id": 7006, "rank": 34, "firstname": "Lucie", "lastname": "Loudova", "paraclimbing_sport_class": null, "sport_class_status": null, "country": "CZE", "federation_id": 17, "rounds": []}, {"athlete_id": 5364, "rank": 34, "firstname": "Karin", "lastname": "Magog", "paraclimbing_sport_class": null, "sport_class_status": null, "country": "GBR", "federation_id": 11, "rounds": []}, {"athlete_id": 7007, "rank": 34, "firstname": "Manuela", "lastname": "Monschein", "paraclimbing_sport_class": null, "sport_class_status": null, "country": "AUT", "federation_id": 16, "rounds": []}, {"athlete_id": 4711, "rank": 38, "firstname": "Jitka", "lastname": "Kuhngaberova", "paraclimbing_sport_class": null, "sport_class_status": null, "country": "CZE", "federation_id": 17, "rounds": []}, {"athlete_id": 6546, "rank": 38, "firstname": "Tamara", "lastname": "Schlemmer", "paraclimbing_sport_class": null, "sport_class_status": null, "country": "GER", "federation_id": 6, "rounds": []}, {"athlete_id": 7008, "rank": 38, "firstname": "Eva", "lastname": "Smejkalova", "paraclimbing_sport_class": null, "sport_class_status": null, "country": "CZE", "federation_id": 17, "rounds": []}]}}, " 3": {"id": 154, "name": "UIAA Worldcup - Graz 1996", "league_id": 1, "league_season_id": 100, "season_id": 9, "starts_at": "1996-12-14 00:00:00 UTC", "ends_at": "1996-12-15 00:00:00 UTC", "local_start_date": "1996-12-14", "local_end_date": "1996-12-15", "timezone": null, "location": "W-Graz", "public_information": {"organiser_name": null, "organiser_url": null, "venue_name": null}, "computed_combined_categories": [], "team_ranking_disciplines": ["lead"], "team_ranking_url": "/api/v1/events/154/team_results/", "categories": ["LEAD Men", "LEAD Women"], "results": {"LEAD Men": [{"athlete_id": 392, "rank": 1, "firstname": "Arnaud", "lastname": "Petit", "paraclimbing_sport_class": null, "sport_class_status": null, "country": "FRA", "federation_id": 10, "rounds": []}, {"athlete_id": 4472, "rank": 2, "firstname": "Cristian", "lastname": "Brenna", "paraclimbing_sport_class": null, "sport_class_status": null, "country": "ITA", "federation_id": 13, "rounds": []}, {"athlete_id": 4464, "rank": 3, "firstname": "Fran\u00e7ois", "lastname": "Petit", "paraclimbing_sport_class": null, "sport_class_status": null, "country": "FRA", "federation_id": 10, "rounds": []}, {"athlete_id": 847, "rank": 4, "firstname": "Luca", "lastname": "Zardini", "paraclimbing_sport_class": null, "sport_class_status": null, "country": "ITA", "federation_id": 13, "rounds": []}, {"athlete_id": 4463, "rank": 5, "firstname": "Christian", "lastname": "Core", "paraclimbing_sport_class": null, "sport_class_status": null, "country": "ITA", "federation_id": 13, "rounds": []}, {"athlete_id": 4602, "rank": 6, "firstname": "Aljosa", "lastname": "Grom", "paraclimbing_sport_class": null, "sport_class_status": null, "country": "SLO", "federation_id": 15, "rounds": []}, {"athlete_id": 4586, "rank": 7, "firstname": "Christian", "lastname": "Bindhammer", "paraclimbing_sport_class": null, "sport_class_status": null, "country": "GER", "federation_id": 6, "rounds": []}, {"athlete_id": 6488, "rank": 7, "firstname": "Elie", "lastname": "Chevieux", "paraclimbing_sport_class": null, "sport_class_status": null, "country": "SUI", "federation_id": 8, "rounds": []}, {"athlete_id": 6465, "rank": 7, "firstname": "Fran\u00e7ois", "lastname": "Lombard", "paraclimbing_sport_class": null, "sport_class_status": null, "country": "FRA", "federation_id": 10, "rounds": []}, {"athlete_id": 6463, "rank": 7, "firstname": "Jean-Baptiste", "lastname": "Tribout", "paraclimbing_sport_class": null, "sport_class_status": null, "country": "FRA", "federation_id": 10, "rounds": []}, {"athlete_id": 4593, "rank": 11, "firstname": "Fran\u00e7ois", "lastname": "Legrand", "paraclimbing_sport_class": null, "sport_class_status": null, "country": "FRA", "federation_id": 10, "rounds": []}, {"athlete_id": 5435, "rank": 12, "firstname": "Frederic", "lastname": "Sarkany", "paraclimbing_sport_class": null, "sport_class_status": null, "country": "BEL", "federation_id": 9, "rounds": []}, {"athlete_id": 4471, "rank": 13, "firstname": "Ludovic", "lastname": "Laurence", "paraclimbing_sport_class": null, "sport_class_status": null, "country": "FRA", "federation_id": 10, "rounds": []}, {"athlete_id": 846, "rank": 14, "firstname": "Luca", "lastname": "Giupponi", "paraclimbing_sport_class": null, "sport_class_status": null, "country": "ITA", "federation_id": 13, "rounds": []}, {"athlete_id": 5047, "rank": 15, "firstname": "Mauro", "lastname": "Calibani", "paraclimbing_sport_class": null, "sport_class_status": null, "country": "ITA", "federation_id": 13, "rounds": []}, {"athlete_id": 4578, "rank": 15, "firstname": "Paul", "lastname": "Dewilde", "paraclimbing_sport_class": null, "sport_class_status": null, "country": "FRA", "federation_id": 10, "rounds": []}, {"athlete_id": 2247, "rank": 15, "firstname": "Yuji", "lastname": "Hirayama", "paraclimbing_sport_class": null, "sport_class_status": null, "country": "JPN", "federation_id": 25, "rounds": []}, {"athlete_id": 6623, "rank": 18, "firstname": "Christoph", "lastname": "Finkel", "paraclimbing_sport_class": null, "sport_class_status": null, "country": "GER", "federation_id": 6, "rounds": []}, {"athlete_id": 6558, "rank": 19, "firstname": "Stefano", "lastname": "Alippi", "paraclimbing_sport_class": null, "sport_class_status": null, "country": "ITA", "federation_id": 13, "rounds": []}, {"athlete_id": 420, "rank": 20, "firstname": "Mathieu", "lastname": "Gallot-Lavallee", "paraclimbing_sport_class": null, "sport_class_status": null, "country": "FRA", "federation_id": 10, "rounds": []}, {"athlete_id": 1467, "rank": 21, "firstname": "Serik", "lastname": "Kazbekov", "paraclimbing_sport_class": null, "sport_class_status": null, "country": "UKR", "federation_id": 18, "rounds": []}, {"athlete_id": 4462, "rank": 22, "firstname": "Pedro", "lastname": "Pons", "paraclimbing_sport_class": null, "sport_class_status": null, "country": "ESP", "federation_id": 12, "rounds": []}, {"athlete_id": 4643, "rank": 23, "firstname": "Evgeny", "lastname": "Ovchinnikov", "paraclimbing_sport_class": null, "sport_class_status": null, "country": "RUS", "federation_id": 7, "rounds": []}, {"athlete_id": 6464, "rank": 24, "firstname": "Patxi", "lastname": "Arocena", "paraclimbing_sport_class": null, "sport_class_status": null, "country": "ESP", "federation_id": 12, "rounds": []}, {"athlete_id": 6596, "rank": 24, "firstname": "Christoph", "lastname": "Bucher", "paraclimbing_sport_class": null, "sport_class_status": null, "country": "GER", "federation_id": 6, "rounds": []}, {"athlete_id": 6999, "rank": 24, "firstname": "Thomas", "lastname": "Feuerstein", "paraclimbing_sport_class": null, "sport_class_status": null, "country": "AUT", "federation_id": 16, "rounds": []}, {"athlete_id": 2030, "rank": 27, "firstname": "Jung-Jun", "lastname": "Son", "paraclimbing_sport_class": null, "sport_class_status": null, "country": "KOR", "federation_id": 21, "rounds": []}, {"athlete_id": 844, "rank": 28, "firstname": "Donato", "lastname": "Lella", "paraclimbing_sport_class": null, "sport_class_status": null, "country": "ITA", "federation_id": 13, "rounds": []}, {"athlete_id": 6947, "rank": 29, "firstname": "Hans", "lastname": "Milewski", "paraclimbing_sport_class": null, "sport_class_status": null, "country": "AUT", "federation_id": 16, "rounds": []}, {"athlete_id": 4465, "rank": 29, "firstname": "Salavat", "lastname": "Rakhmetov", "paraclimbing_sport_class": null, "sport_class_status": null, "country": "RUS", "federation_id": 7, "rounds": []}, {"athlete_id": 4600, "rank": 31, "firstname": "Iouri", "lastname": "Douloub", "paraclimbing_sport_class": null, "sport_class_status": null, "country": "RUS", "federation_id": 7, "rounds": []}, {"athlete_id": 6753, "rank": 31, "firstname": "Florian", "lastname": "Hage", "paraclimbing_sport_class": null, "sport_class_status": null, "country": "GER", "federation_id": 6, "rounds": []}, {"athlete_id": 6902, "rank": 33, "firstname": "Serguei", "lastname": "Chemoulinkine", "paraclimbing_sport_class": null, "sport_class_status": null, "country": "RUS", "federation_id": 7, "rounds": []}, {"athlete_id": 1115, "rank": 33, "firstname": "Jurij", "lastname": "Golob", "paraclimbing_sport_class": null, "sport_class_status": null, "country": "SLO", "federation_id": 15, "rounds": []}, {"athlete_id": 4577, "rank": 33, "firstname": "Simon", "lastname": "Fasnacht Wandeler", "paraclimbing_sport_class": null, "sport_class_status": null, "country": "SUI", "federation_id": 8, "rounds": []}, {"athlete_id": 6893, "rank": 36, "firstname": "Neil", "lastname": "Carson", "paraclimbing_sport_class": null, "sport_class_status": null, "country": "GBR", "federation_id": 11, "rounds": []}, {"athlete_id": 402, "rank": 36, "firstname": "Daniel", "lastname": "DU LAC", "paraclimbing_sport_class": null, "sport_class_status": null, "country": "FRA", "federation_id": 10, "rounds": []}, {"athlete_id": 3576, "rank": 36, "firstname": "Wouter", "lastname": "Jongeneelen", "paraclimbing_sport_class": null, "sport_class_status": null, "country": "NED", "federation_id": 50, "rounds": []}, {"athlete_id": 6948, "rank": 39, "firstname": "Wolfgang", "lastname": "Widder", "paraclimbing_sport_class": null, "sport_class_status": null, "country": "GER", "federation_id": 6, "rounds": []}, {"athlete_id": 843, "rank": 40, "firstname": "Alberto", "lastname": "Gnerro", "paraclimbing_sport_class": null, "sport_class_status": null, "country": "ITA", "federation_id": 13, "rounds": []}, {"athlete_id": 6497, "rank": 40, "firstname": "Vili", "lastname": "Gucek", "paraclimbing_sport_class": null, "sport_class_status": null, "country": "SLO", "federation_id": 15, "rounds": []}, {"athlete_id": 4580, "rank": 42, "firstname": "David", "lastname": "Caude", "paraclimbing_sport_class": null, "sport_class_status": null, "country": "FRA", "federation_id": 10, "rounds": []}, {"athlete_id": 6594, "rank": 42, "firstname": "Kairat", "lastname": "Rakhmetov", "paraclimbing_sport_class": null, "sport_class_status": null, "country": "KAZ", "federation_id": 47, "rounds": []}, {"athlete_id": 4597, "rank": 44, "firstname": "Andreas", "lastname": "Bindhammer", "paraclimbing_sport_class": null, "sport_class_status": null, "country": "GER", "federation_id": 6, "rounds": []}, {"athlete_id": 4477, "rank": 44, "firstname": "Timmy", "lastname": "Fairfield", "paraclimbing_sport_class": null, "sport_class_status": null, "country": "CAN", "federation_id": 19, "rounds": []}, {"athlete_id": 2416, "rank": 44, "firstname": "Kalin", "lastname": "Garbov", "paraclimbing_sport_class": null, "sport_class_status": null, "country": "BUL", "federation_id": 26, "rounds": []}, {"athlete_id": 6950, "rank": 44, "firstname": "Sebastian", "lastname": "Zasadzki", "paraclimbing_sport_class": null, "sport_class_status": null, "country": "POL", "federation_id": 36, "rounds": []}, {"athlete_id": 5264, "rank": 48, "firstname": "Pavel", "lastname": "Koran", "paraclimbing_sport_class": null, "sport_class_status": null, "country": "CZE", "federation_id": 17, "rounds": []}, {"athlete_id": 4576, "rank": 49, "firstname": "Yevgen", "lastname": "Kryvosheytsev", "paraclimbing_sport_class": null, "sport_class_status": null, "country": "UKR", "federation_id": 18, "rounds": []}, {"athlete_id": 7009, "rank": 50, "firstname": "Ben", "lastname": "Bransby", "paraclimbing_sport_class": null, "sport_class_status": null, "country": "GBR", "federation_id": 11, "rounds": []}, {"athlete_id": 4618, "rank": 51, "firstname": "Serguei", "lastname": "Nourmamatov", "paraclimbing_sport_class": null, "sport_class_status": null, "country": "RUS", "federation_id": 7, "rounds": []}, {"athlete_id": 2753, "rank": 51, "firstname": "Anton", "lastname": "Pacek", "paraclimbing_sport_class": null, "sport_class_status": null, "country": "SVK", "federation_id": 34, "rounds": []}, {"athlete_id": 6974, "rank": 53, "firstname": "Gotzon", "lastname": "Gardeazabal", "paraclimbing_sport_class": null, "sport_class_status": null, "country": "ESP", "federation_id": 12, "rounds": []}, {"athlete_id": 4588, "rank": 53, "firstname": "Marek", "lastname": "Havlik", "paraclimbing_sport_class": null, "sport_class_status": null, "country": "CZE", "federation_id": 17, "rounds": []}, {"athlete_id": 4581, "rank": 53, "firstname": "Tomasz", "lastname": "Oleksy", "paraclimbing_sport_class": null, "sport_class_status": null, "country": "POL", "federation_id": 36, "rounds": []}, {"athlete_id": 2417, "rank": 53, "firstname": "Milen", "lastname": "Videnovski", "paraclimbing_sport_class": null, "sport_class_status": null, "country": "BUL", "federation_id": 26, "rounds": []}, {"athlete_id": 4713, "rank": 57, "firstname": "Franci", "lastname": "Jensterle", "paraclimbing_sport_class": null, "sport_class_status": null, "country": "SLO", "federation_id": 15, "rounds": []}, {"athlete_id": 6468, "rank": 58, "firstname": "Stefan", "lastname": "F\u00fcrst", "paraclimbing_sport_class": null, "sport_class_status": null, "country": "AUT", "federation_id": 16, "rounds": []}, {"athlete_id": 6930, "rank": 58, "firstname": "Martin", "lastname": "Reimers", "paraclimbing_sport_class": null, "sport_class_status": null, "country": "NOR", "federation_id": 39, "rounds": []}, {"athlete_id": 5076, "rank": 60, "firstname": "Christopher", "lastname": "Cubitt", "paraclimbing_sport_class": null, "sport_class_status": null, "country": "GBR", "federation_id": 11, "rounds": []}, {"athlete_id": 4734, "rank": 61, "firstname": "Kyu-Bog", "lastname": "Cho", "paraclimbing_sport_class": null, "sport_class_status": null, "country": "KOR", "federation_id": 21, "rounds": []}, {"athlete_id": 6715, "rank": 61, "firstname": "Ionel", "lastname": "Ene", "paraclimbing_sport_class": null, "sport_class_status": null, "country": "ROU", "federation_id": 33, "rounds": []}, {"athlete_id": 6797, "rank": 61, "firstname": "Michael", "lastname": "Lea", "paraclimbing_sport_class": null, "sport_class_status": null, "country": "GBR", "federation_id": 11, "rounds": []}, {"athlete_id": 4685, "rank": 61, "firstname": "Matthias", "lastname": "Trottmann", "paraclimbing_sport_class": null, "sport_class_status": null, "country": "SUI", "federation_id": 8, "rounds": []}, {"athlete_id": 6836, "rank": 65, "firstname": "Milan", "lastname": "Benian", "paraclimbing_sport_class": null, "sport_class_status": null, "country": "CZE", "federation_id": 17, "rounds": []}, {"athlete_id": 2752, "rank": 66, "firstname": "Andrej", "lastname": "Chrastina", "paraclimbing_sport_class": null, "sport_class_status": null, "country": "SVK", "federation_id": 34, "rounds": []}, {"athlete_id": 6971, "rank": 66, "firstname": "Paal Benum", "lastname": "Reiten", "paraclimbing_sport_class": null, "sport_class_status": null, "country": "NOR", "federation_id": 39, "rounds": []}, {"athlete_id": 5128, "rank": 66, "firstname": "Takaaki", "lastname": "Tsuiki", "paraclimbing_sport_class": null, "sport_class_status": null, "country": "JPN", "federation_id": 25, "rounds": []}, {"athlete_id": 6959, "rank": 69, "firstname": "Marcin", "lastname": "Bartocha", "paraclimbing_sport_class": null, "sport_class_status": null, "country": "POL", "federation_id": 36, "rounds": []}, {"athlete_id": 6927, "rank": 70, "firstname": "Peter", "lastname": "Kmosko", "paraclimbing_sport_class": null, "sport_class_status": null, "country": "SVK", "federation_id": 34, "rounds": []}, {"athlete_id": 6998, "rank": 71, "firstname": "Gyula", "lastname": "Dozsa", "paraclimbing_sport_class": null, "sport_class_status": null, "country": "HUN", "federation_id": 23, "rounds": []}, {"athlete_id": 5056, "rank": 71, "firstname": "Hee-Jo", "lastname": "Kim", "paraclimbing_sport_class": null, "sport_class_status": null, "country": "KOR", "federation_id": 21, "rounds": []}, {"athlete_id": 5162, "rank": 73, "firstname": "Ilfir", "lastname": "Khakimianov", "paraclimbing_sport_class": null, "sport_class_status": null, "country": "RUS", "federation_id": 7, "rounds": []}, {"athlete_id": 6962, "rank": 73, "firstname": "Janos", "lastname": "Nagy", "paraclimbing_sport_class": null, "sport_class_status": null, "country": "HUN", "federation_id": 23, "rounds": []}, {"athlete_id": 4582, "rank": 75, "firstname": "Matej", "lastname": "Sova", "paraclimbing_sport_class": null, "sport_class_status": null, "country": "SLO", "federation_id": 15, "rounds": []}], "LEAD Women": [{"athlete_id": 4530, "rank": 1, "firstname": "Liv", "lastname": "Sansoz", "paraclimbing_sport_class": null, "sport_class_status": null, "country": "FRA", "federation_id": 10, "rounds": []}, {"athlete_id": 6728, "rank": 2, "firstname": "Laurence", "lastname": "Guyon", "paraclimbing_sport_class": null, "sport_class_status": null, "country": "FRA", "federation_id": 10, "rounds": []}, {"athlete_id": 4529, "rank": 3, "firstname": "St\u00e9phanie", "lastname": "Bodet", "paraclimbing_sport_class": null, "sport_class_status": null, "country": "FRA", "federation_id": 10, "rounds": []}, {"athlete_id": 6533, "rank": 4, "firstname": "Natalie", "lastname": "Richer", "paraclimbing_sport_class": null, "sport_class_status": null, "country": "FRA", "federation_id": 10, "rounds": []}, {"athlete_id": 6727, "rank": 5, "firstname": "Marie", "lastname": "Guillet", "paraclimbing_sport_class": null, "sport_class_status": null, "country": "FRA", "federation_id": 10, "rounds": []}, {"athlete_id": 306, "rank": 5, "firstname": "Muriel", "lastname": "Sarkany", "paraclimbing_sport_class": null, "sport_class_status": null, "country": "BEL", "federation_id": 9, "rounds": []}, {"athlete_id": 5109, "rank": 7, "firstname": "Venera", "lastname": "Chereshneva", "paraclimbing_sport_class": null, "sport_class_status": null, "country": "RUS", "federation_id": 7, "rounds": []}, {"athlete_id": 4449, "rank": 8, "firstname": "Elena", "lastname": "Choumilova", "paraclimbing_sport_class": null, "sport_class_status": null, "country": "RUS", "federation_id": 7, "rounds": []}, {"athlete_id": 4549, "rank": 9, "firstname": "Luisa", "lastname": "Iovane", "paraclimbing_sport_class": null, "sport_class_status": null, "country": "ITA", "federation_id": 13, "rounds": []}, {"athlete_id": 427, "rank": 10, "firstname": "Cecile", "lastname": "Avezou", "paraclimbing_sport_class": null, "sport_class_status": null, "country": "FRA", "federation_id": 10, "rounds": []}, {"athlete_id": 4540, "rank": 11, "firstname": "Elena", "lastname": "Ovtchinnikova", "paraclimbing_sport_class": null, "sport_class_status": null, "country": "USA", "federation_id": 20, "rounds": []}, {"athlete_id": 6545, "rank": 12, "firstname": "Metka", "lastname": "Lukancic", "paraclimbing_sport_class": null, "sport_class_status": null, "country": "SLO", "federation_id": 15, "rounds": []}, {"athlete_id": 4720, "rank": 13, "firstname": "Marietta", "lastname": "Uhden", "paraclimbing_sport_class": null, "sport_class_status": null, "country": "GER", "federation_id": 6, "rounds": []}, {"athlete_id": 4486, "rank": 14, "firstname": "Martina", "lastname": "Cufar", "paraclimbing_sport_class": null, "sport_class_status": null, "country": "SLO", "federation_id": 15, "rounds": []}, {"athlete_id": 4719, "rank": 14, "firstname": "Mi-Sun", "lastname": "Go", "paraclimbing_sport_class": null, "sport_class_status": null, "country": "KOR", "federation_id": 21, "rounds": []}, {"athlete_id": 6694, "rank": 16, "firstname": "Mirjam", "lastname": "Verbeek", "paraclimbing_sport_class": null, "sport_class_status": null, "country": "NED", "federation_id": 50, "rounds": []}, {"athlete_id": 4565, "rank": 17, "firstname": "Zosia", "lastname": "Podgorbounskikh", "paraclimbing_sport_class": null, "sport_class_status": null, "country": "RUS", "federation_id": 7, "rounds": []}, {"athlete_id": 6992, "rank": 18, "firstname": "Katarina", "lastname": "Stremfelj", "paraclimbing_sport_class": null, "sport_class_status": null, "country": "SLO", "federation_id": 15, "rounds": []}, {"athlete_id": 6866, "rank": 19, "firstname": "Mia", "lastname": "Axon", "paraclimbing_sport_class": null, "sport_class_status": null, "country": "USA", "federation_id": 20, "rounds": []}, {"athlete_id": 1203, "rank": 20, "firstname": "Bettina", "lastname": "sch\u00f6pf", "paraclimbing_sport_class": null, "sport_class_status": null, "country": "AUT", "federation_id": 16, "rounds": []}, {"athlete_id": 6583, "rank": 21, "firstname": "Yulia", "lastname": "Inozemtseva", "paraclimbing_sport_class": null, "sport_class_status": null, "country": "RUS", "federation_id": 7, "rounds": []}, {"athlete_id": 6978, "rank": 22, "firstname": "Iva", "lastname": "Hartmann", "paraclimbing_sport_class": null, "sport_class_status": null, "country": "SUI", "federation_id": 8, "rounds": []}, {"athlete_id": 5865, "rank": 22, "firstname": "Margaux", "lastname": "Hilly", "paraclimbing_sport_class": null, "sport_class_status": null, "country": "FRA", "federation_id": 10, "rounds": []}, {"athlete_id": 7005, "rank": 22, "firstname": "Blaza", "lastname": "Klemencic", "paraclimbing_sport_class": null, "sport_class_status": null, "country": "SLO", "federation_id": 15, "rounds": []}, {"athlete_id": 6839, "rank": 22, "firstname": "Irene", "lastname": "Steindl", "paraclimbing_sport_class": null, "sport_class_status": null, "country": "AUT", "federation_id": 16, "rounds": []}, {"athlete_id": 6549, "rank": 26, "firstname": "Karin", "lastname": "Kavoussi", "paraclimbing_sport_class": null, "sport_class_status": null, "country": "AUT", "federation_id": 16, "rounds": []}, {"athlete_id": 4455, "rank": 26, "firstname": "Chlo\u00e9", "lastname": "Minoret", "paraclimbing_sport_class": null, "sport_class_status": null, "country": "FRA", "federation_id": 10, "rounds": []}, {"athlete_id": 6895, "rank": 28, "firstname": "Silvia", "lastname": "Pearsons", "paraclimbing_sport_class": null, "sport_class_status": null, "country": "GBR", "federation_id": 11, "rounds": []}, {"athlete_id": 4461, "rank": 28, "firstname": "Romana", "lastname": "Savic", "paraclimbing_sport_class": null, "sport_class_status": null, "country": "SLO", "federation_id": 15, "rounds": []}, {"athlete_id": 7004, "rank": 30, "firstname": "Delphine", "lastname": "Pigneur", "paraclimbing_sport_class": null, "sport_class_status": null, "country": "FRA", "federation_id": 10, "rounds": []}, {"athlete_id": 4555, "rank": 31, "firstname": "Anne", "lastname": "Arran", "paraclimbing_sport_class": null, "sport_class_status": null, "country": "GBR", "federation_id": 11, "rounds": []}, {"athlete_id": 4450, "rank": 32, "firstname": "Myriam", "lastname": "Motteau", "paraclimbing_sport_class": null, "sport_class_status": null, "country": "FRA", "federation_id": 10, "rounds": []}, {"athlete_id": 6555, "rank": 32, "firstname": "Catherine", "lastname": "Vallet", "paraclimbing_sport_class": null, "sport_class_status": null, "country": "FRA", "federation_id": 10, "rounds": []}, {"athlete_id": 4538, "rank": 34, "firstname": "Iwona", "lastname": "Gronkiewicz-Marcisz", "paraclimbing_sport_class": null, "sport_class_status": null, "country": "POL", "federation_id": 36, "rounds": []}, {"athlete_id": 4485, "rank": 35, "firstname": "Kim", "lastname": "Anthoni", "paraclimbing_sport_class": null, "sport_class_status": null, "country": "BEL", "federation_id": 9, "rounds": []}, {"athlete_id": 6957, "rank": 35, "firstname": "Ines", "lastname": "Bischoff", "paraclimbing_sport_class": null, "sport_class_status": null, "country": "GER", "federation_id": 6, "rounds": []}, {"athlete_id": 5096, "rank": 37, "firstname": "Eva", "lastname": "Nieselt", "paraclimbing_sport_class": null, "sport_class_status": null, "country": "GER", "federation_id": 6, "rounds": []}, {"athlete_id": 4532, "rank": 38, "firstname": "Renata", "lastname": "Piszczek", "paraclimbing_sport_class": null, "sport_class_status": null, "country": "POL", "federation_id": 36, "rounds": []}, {"athlete_id": 5364, "rank": 39, "firstname": "Karin", "lastname": "Magog", "paraclimbing_sport_class": null, "sport_class_status": null, "country": "GBR", "federation_id": 11, "rounds": []}, {"athlete_id": 39, "rank": 39, "firstname": "Mayya", "lastname": "Piratinskaya", "paraclimbing_sport_class": null, "sport_class_status": null, "country": "RUS", "federation_id": 7, "rounds": []}, {"athlete_id": 7008, "rank": 41, "firstname": "Eva", "lastname": "Smejkalova", "paraclimbing_sport_class": null, "sport_class_status": null, "country": "CZE", "federation_id": 17, "rounds": []}, {"athlete_id": 4452, "rank": 42, "firstname": "Ingela", "lastname": "Nilsson", "paraclimbing_sport_class": null, "sport_class_status": null, "country": "SWE", "federation_id": 32, "rounds": []}, {"athlete_id": 7010, "rank": 43, "firstname": "Monika", "lastname": "Niedbalska", "paraclimbing_sport_class": null, "sport_class_status": null, "country": "POL", "federation_id": 36, "rounds": []}, {"athlete_id": 7007, "rank": 44, "firstname": "Manuela", "lastname": "Monschein", "paraclimbing_sport_class": null, "sport_class_status": null, "country": "AUT", "federation_id": 16, "rounds": []}, {"athlete_id": 7011, "rank": 45, "firstname": "Oliwia", "lastname": "Bechyne", "paraclimbing_sport_class": null, "sport_class_status": null, "country": "POL", "federation_id": 36, "rounds": []}, {"athlete_id": 7012, "rank": 46, "firstname": "Eliza", "lastname": "Czerwinska", "paraclimbing_sport_class": null, "sport_class_status": null, "country": "POL", "federation_id": 36, "rounds": []}, {"athlete_id": 7013, "rank": 47, "firstname": "Pia", "lastname": "Pylv\u00e4n\u00e4inen", "paraclimbing_sport_class": null, "sport_class_status": null, "country": "FIN", "federation_id": 35, "rounds": []}, {"athlete_id": 5429, "rank": 48, "firstname": "Anna", "lastname": "Jarek", "paraclimbing_sport_class": null, "sport_class_status": null, "country": "POL", "federation_id": 36, "rounds": []}, {"athlete_id": 4559, "rank": 49, "firstname": "Ulla", "lastname": "Walder", "paraclimbing_sport_class": null, "sport_class_status": null, "country": "ITA", "federation_id": 13, "rounds": []}]}}}}