{
    "id": 391,
    "name": "UIAA Worldcup (L+S) - Veliko Tarnovo (BUL) 2005",
    "league_id": 1,
    "league_season_id": 208,
    "season_id": 18,
    "starts_at": "2005-04-23 00:00:00 UTC",
    "ends_at": "2005-04-25 00:00:00 UTC",
    "local_start_date": "2005-04-23",
    "local_end_date": "2005-04-25",
    "timezone": null,
    "location": "Veliko Tarnovo (L+S)",
    "public_information": {
        "organiser_name": null,
        "organiser_url": null,
        "venue_name": null
    },
    "computed_combined_categories": [],
    "team_ranking_disciplines": [
        "lead",
        "speed"
    ],
    "team_ranking_url": "/api/v1/events/391/team_results/",
    "categories": [
        "LEAD Men",
        "LEAD Women",
        "SPEED Men",
        "SPEED Women"
    ],
    "results": {
        "LEAD Men": [
            {
                "athlete_id": 845,
                "rank": 1,
                "firstname": "Flavio",
                "lastname": "Crespi",
                "paraclimbing_sport_class": null,
                "sport_class_status": null,
                "country": "ITA",
                "federation_id": 13,
                "rounds": []
            },
            {
                "athlete_id": 3577,
                "rank": 2,
                "firstname": "Jorg",
                "lastname": "Verhoeven",
                "paraclimbing_sport_class": null,
                "sport_class_status": null,
                "country": "NED",
                "federation_id": 50,
                "rounds": []
            },
            {
                "athlete_id": 3129,
                "rank": 3,
                "firstname": "C\u00e9dric",
                "lastname": "Lachat",
                "paraclimbing_sport_class": null,
                "sport_class_status": null,
                "country": "SUI",
                "federation_id": 8,
                "rounds": []
            },
            {
                "athlete_id": 4715,
                "rank": 4,
                "firstname": "Ivaylo",
                "lastname": "Krastev",
                "paraclimbing_sport_class": null,
                "sport_class_status": null,
                "country": "BUL",
                "federation_id": 26,
                "rounds": []
            },
            {
                "athlete_id": 847,
                "rank": 5,
                "firstname": "Luca",
                "lastname": "Zardini",
                "paraclimbing_sport_class": null,
                "sport_class_status": null,
                "country": "ITA",
                "federation_id": 13,
                "rounds": []
            },
            {
                "athlete_id": 2247,
                "rank": 6,
                "firstname": "Yuji",
                "lastname": "Hirayama",
                "paraclimbing_sport_class": null,
                "sport_class_status": null,
                "country": "JPN",
                "federation_id": 25,
                "rounds": []
            },
            {
                "athlete_id": 772,
                "rank": 7,
                "firstname": "Patxi",
                "lastname": "Usobiaga Lakunza",
                "paraclimbing_sport_class": null,
                "sport_class_status": null,
                "country": "ESP",
                "federation_id": 12,
                "rounds": []
            },
            {
                "athlete_id": 773,
                "rank": 8,
                "firstname": "Ram\u00f3n ",
                "lastname": "Julian  Puigblanque",
                "paraclimbing_sport_class": null,
                "sport_class_status": null,
                "country": "ESP",
                "federation_id": 12,
                "rounds": []
            },
            {
                "athlete_id": 1356,
                "rank": 9,
                "firstname": "Tom\u00e1s",
                "lastname": "Mr\u00e1zek",
                "paraclimbing_sport_class": null,
                "sport_class_status": null,
                "country": "CZE",
                "federation_id": 17,
                "rounds": []
            },
            {
                "athlete_id": 4575,
                "rank": 10,
                "firstname": "Maksym",
                "lastname": "Petrenko",
                "paraclimbing_sport_class": null,
                "sport_class_status": null,
                "country": "UKR",
                "federation_id": 18,
                "rounds": []
            },
            {
                "athlete_id": 2416,
                "rank": 11,
                "firstname": "Kalin",
                "lastname": "Garbov",
                "paraclimbing_sport_class": null,
                "sport_class_status": null,
                "country": "BUL",
                "federation_id": 26,
                "rounds": []
            },
            {
                "athlete_id": 4690,
                "rank": 12,
                "firstname": "Fabien",
                "lastname": "Dugit",
                "paraclimbing_sport_class": null,
                "sport_class_status": null,
                "country": "FRA",
                "federation_id": 10,
                "rounds": []
            },
            {
                "athlete_id": 5192,
                "rank": 13,
                "firstname": "Timo",
                "lastname": "Preu\u00dfler",
                "paraclimbing_sport_class": null,
                "sport_class_status": null,
                "country": "GER",
                "federation_id": 6,
                "rounds": []
            },
            {
                "athlete_id": 4581,
                "rank": 14,
                "firstname": "Tomasz",
                "lastname": "Oleksy",
                "paraclimbing_sport_class": null,
                "sport_class_status": null,
                "country": "POL",
                "federation_id": 36,
                "rounds": []
            },
            {
                "athlete_id": 426,
                "rank": 15,
                "firstname": "Sylvain",
                "lastname": "Millet",
                "paraclimbing_sport_class": null,
                "sport_class_status": null,
                "country": "FRA",
                "federation_id": 10,
                "rounds": []
            },
            {
                "athlete_id": 2757,
                "rank": 16,
                "firstname": "Juraj",
                "lastname": "Repcik",
                "paraclimbing_sport_class": null,
                "sport_class_status": null,
                "country": "SVK",
                "federation_id": 34,
                "rounds": []
            },
            {
                "athlete_id": 2417,
                "rank": 16,
                "firstname": "Milen",
                "lastname": "Videnovski",
                "paraclimbing_sport_class": null,
                "sport_class_status": null,
                "country": "BUL",
                "federation_id": 26,
                "rounds": []
            },
            {
                "athlete_id": 5256,
                "rank": 18,
                "firstname": "Eduard",
                "lastname": "Marin Garcia",
                "paraclimbing_sport_class": null,
                "sport_class_status": null,
                "country": "ESP",
                "federation_id": 12,
                "rounds": []
            },
            {
                "athlete_id": 4587,
                "rank": 19,
                "firstname": "Vadim",
                "lastname": "Vinokur",
                "paraclimbing_sport_class": null,
                "sport_class_status": null,
                "country": "USA",
                "federation_id": 20,
                "rounds": []
            },
            {
                "athlete_id": 5393,
                "rank": 20,
                "firstname": "Daniel",
                "lastname": "Winkler",
                "paraclimbing_sport_class": null,
                "sport_class_status": null,
                "country": "SUI",
                "federation_id": 8,
                "rounds": []
            },
            {
                "athlete_id": 5510,
                "rank": 21,
                "firstname": "Boyko",
                "lastname": "Lalov",
                "paraclimbing_sport_class": null,
                "sport_class_status": null,
                "country": "BUL",
                "federation_id": 26,
                "rounds": []
            },
            {
                "athlete_id": 5465,
                "rank": 22,
                "firstname": "Fabrizio",
                "lastname": "Droetto",
                "paraclimbing_sport_class": null,
                "sport_class_status": null,
                "country": "ITA",
                "federation_id": 13,
                "rounds": []
            },
            {
                "athlete_id": 53,
                "rank": 23,
                "firstname": "Dmitrii",
                "lastname": "Sharafutdinov",
                "paraclimbing_sport_class": null,
                "sport_class_status": null,
                "country": "RUS",
                "federation_id": 7,
                "rounds": []
            },
            {
                "athlete_id": 4777,
                "rank": 24,
                "firstname": "Markus",
                "lastname": "Hoppe",
                "paraclimbing_sport_class": null,
                "sport_class_status": null,
                "country": "GER",
                "federation_id": 6,
                "rounds": []
            },
            {
                "athlete_id": 4819,
                "rank": 25,
                "firstname": "Blagovest",
                "lastname": "Lazarov",
                "paraclimbing_sport_class": null,
                "sport_class_status": null,
                "country": "BUL",
                "federation_id": 26,
                "rounds": []
            },
            {
                "athlete_id": 4826,
                "rank": 26,
                "firstname": "Stefan",
                "lastname": "Avramov",
                "paraclimbing_sport_class": null,
                "sport_class_status": null,
                "country": "BUL",
                "federation_id": 26,
                "rounds": []
            },
            {
                "athlete_id": 4864,
                "rank": 26,
                "firstname": "Ivan",
                "lastname": "Kaurov",
                "paraclimbing_sport_class": null,
                "sport_class_status": null,
                "country": "RUS",
                "federation_id": 7,
                "rounds": []
            },
            {
                "athlete_id": 5151,
                "rank": 28,
                "firstname": "Hidekazu",
                "lastname": "Ito",
                "paraclimbing_sport_class": null,
                "sport_class_status": null,
                "country": "JPN",
                "federation_id": 25,
                "rounds": []
            },
            {
                "athlete_id": 4470,
                "rank": 29,
                "firstname": "Alexandre",
                "lastname": "Chabot",
                "paraclimbing_sport_class": null,
                "sport_class_status": null,
                "country": "FRA",
                "federation_id": 10,
                "rounds": []
            },
            {
                "athlete_id": 5409,
                "rank": 30,
                "firstname": "Philipp",
                "lastname": "Magin",
                "paraclimbing_sport_class": null,
                "sport_class_status": null,
                "country": "GER",
                "federation_id": 6,
                "rounds": []
            },
            {
                "athlete_id": 5511,
                "rank": 30,
                "firstname": "Andriy",
                "lastname": "Tishchenko",
                "paraclimbing_sport_class": null,
                "sport_class_status": null,
                "country": "UKR",
                "federation_id": 18,
                "rounds": []
            },
            {
                "athlete_id": 419,
                "rank": 32,
                "firstname": "Micha\u00ebl",
                "lastname": "Fuselier",
                "paraclimbing_sport_class": null,
                "sport_class_status": null,
                "country": "FRA",
                "federation_id": 10,
                "rounds": []
            },
            {
                "athlete_id": 5169,
                "rank": 33,
                "firstname": "Marat",
                "lastname": "Sadyrov",
                "paraclimbing_sport_class": null,
                "sport_class_status": null,
                "country": "RUS",
                "federation_id": 7,
                "rounds": []
            },
            {
                "athlete_id": 2925,
                "rank": 33,
                "firstname": "LEI",
                "lastname": "ZHAO",
                "paraclimbing_sport_class": null,
                "sport_class_status": null,
                "country": "CHN",
                "federation_id": 37,
                "rounds": []
            },
            {
                "athlete_id": 4716,
                "rank": 35,
                "firstname": "Klemen",
                "lastname": "Becan",
                "paraclimbing_sport_class": null,
                "sport_class_status": null,
                "country": "SLO",
                "federation_id": 15,
                "rounds": []
            },
            {
                "athlete_id": 437,
                "rank": 35,
                "firstname": "Romain",
                "lastname": "Desgranges",
                "paraclimbing_sport_class": null,
                "sport_class_status": null,
                "country": "FRA",
                "federation_id": 10,
                "rounds": []
            },
            {
                "athlete_id": 4643,
                "rank": 37,
                "firstname": "Evgeny",
                "lastname": "Ovchinnikov",
                "paraclimbing_sport_class": null,
                "sport_class_status": null,
                "country": "RUS",
                "federation_id": 7,
                "rounds": []
            },
            {
                "athlete_id": 5512,
                "rank": 38,
                "firstname": "Milos",
                "lastname": "Stosic",
                "paraclimbing_sport_class": null,
                "sport_class_status": null,
                "country": "SRB",
                "federation_id": 56,
                "rounds": []
            }
        ],
        "LEAD Women": [
            {
                "athlete_id": 1207,
                "rank": 1,
                "firstname": "Angela",
                "lastname": "Eiter",
                "paraclimbing_sport_class": null,
                "sport_class_status": null,
                "country": "AUT",
                "federation_id": 16,
                "rounds": []
            },
            {
                "athlete_id": 438,
                "rank": 2,
                "firstname": "Caroline",
                "lastname": "Ciavaldini",
                "paraclimbing_sport_class": null,
                "sport_class_status": null,
                "country": "FRA",
                "federation_id": 10,
                "rounds": []
            },
            {
                "athlete_id": 1119,
                "rank": 2,
                "firstname": "Natalija",
                "lastname": "Gros",
                "paraclimbing_sport_class": null,
                "sport_class_status": null,
                "country": "SLO",
                "federation_id": 15,
                "rounds": []
            },
            {
                "athlete_id": 306,
                "rank": 4,
                "firstname": "Muriel",
                "lastname": "Sarkany",
                "paraclimbing_sport_class": null,
                "sport_class_status": null,
                "country": "BEL",
                "federation_id": 9,
                "rounds": []
            },
            {
                "athlete_id": 1121,
                "rank": 5,
                "firstname": "Maja",
                "lastname": "Stremfelj",
                "paraclimbing_sport_class": null,
                "sport_class_status": null,
                "country": "SLO",
                "federation_id": 15,
                "rounds": []
            },
            {
                "athlete_id": 4542,
                "rank": 6,
                "firstname": "Olena",
                "lastname": "Kryvonis",
                "paraclimbing_sport_class": null,
                "sport_class_status": null,
                "country": "UKR",
                "federation_id": 18,
                "rounds": []
            },
            {
                "athlete_id": 2251,
                "rank": 7,
                "firstname": "Yuka",
                "lastname": "Kobayashi",
                "paraclimbing_sport_class": null,
                "sport_class_status": null,
                "country": "JPN",
                "federation_id": 25,
                "rounds": []
            },
            {
                "athlete_id": 848,
                "rank": 8,
                "firstname": "Jenny",
                "lastname": "Lavarda",
                "paraclimbing_sport_class": null,
                "sport_class_status": null,
                "country": "ITA",
                "federation_id": 13,
                "rounds": []
            },
            {
                "athlete_id": 5401,
                "rank": 9,
                "firstname": "Caroline",
                "lastname": "Januel",
                "paraclimbing_sport_class": null,
                "sport_class_status": null,
                "country": "FRA",
                "federation_id": 10,
                "rounds": []
            },
            {
                "athlete_id": 4455,
                "rank": 10,
                "firstname": "Chlo\u00e9",
                "lastname": "Minoret",
                "paraclimbing_sport_class": null,
                "sport_class_status": null,
                "country": "FRA",
                "federation_id": 10,
                "rounds": []
            },
            {
                "athlete_id": 5125,
                "rank": 11,
                "firstname": "Lucka",
                "lastname": "Franko",
                "paraclimbing_sport_class": null,
                "sport_class_status": null,
                "country": "SLO",
                "federation_id": 15,
                "rounds": []
            },
            {
                "athlete_id": 1202,
                "rank": 12,
                "firstname": "Barbara",
                "lastname": "Bacher",
                "paraclimbing_sport_class": null,
                "sport_class_status": null,
                "country": "AUT",
                "federation_id": 16,
                "rounds": []
            },
            {
                "athlete_id": 4535,
                "rank": 12,
                "firstname": "Alexandra",
                "lastname": "Eyer",
                "paraclimbing_sport_class": null,
                "sport_class_status": null,
                "country": "SUI",
                "federation_id": 8,
                "rounds": []
            },
            {
                "athlete_id": 309,
                "rank": 14,
                "firstname": "Chlo\u00e9",
                "lastname": "Graftiaux",
                "paraclimbing_sport_class": null,
                "sport_class_status": null,
                "country": "BEL",
                "federation_id": 9,
                "rounds": []
            },
            {
                "athlete_id": 1209,
                "rank": 15,
                "firstname": "Katharina",
                "lastname": "Saurwein",
                "paraclimbing_sport_class": null,
                "sport_class_status": null,
                "country": "AUT",
                "federation_id": 16,
                "rounds": []
            },
            {
                "athlete_id": 4702,
                "rank": 16,
                "firstname": "Olena",
                "lastname": "Ostapenko",
                "paraclimbing_sport_class": null,
                "sport_class_status": null,
                "country": "UKR",
                "federation_id": 18,
                "rounds": []
            },
            {
                "athlete_id": 4543,
                "rank": 16,
                "firstname": "Gerda",
                "lastname": "Raffetseder",
                "paraclimbing_sport_class": null,
                "sport_class_status": null,
                "country": "AUT",
                "federation_id": 16,
                "rounds": []
            },
            {
                "athlete_id": 44,
                "rank": 18,
                "firstname": "Olga",
                "lastname": "Iakovleva",
                "paraclimbing_sport_class": null,
                "sport_class_status": null,
                "country": "RUS",
                "federation_id": 7,
                "rounds": []
            },
            {
                "athlete_id": 4756,
                "rank": 19,
                "firstname": "Olga",
                "lastname": "Shalagina",
                "paraclimbing_sport_class": null,
                "sport_class_status": null,
                "country": "UKR",
                "federation_id": 18,
                "rounds": []
            },
            {
                "athlete_id": 4640,
                "rank": 20,
                "firstname": "Elodie",
                "lastname": "Giroux",
                "paraclimbing_sport_class": null,
                "sport_class_status": null,
                "country": "FRA",
                "federation_id": 10,
                "rounds": []
            },
            {
                "athlete_id": 4454,
                "rank": 21,
                "firstname": "Ina",
                "lastname": "Dzhambazova",
                "paraclimbing_sport_class": null,
                "sport_class_status": null,
                "country": "BUL",
                "federation_id": 26,
                "rounds": []
            },
            {
                "athlete_id": 5294,
                "rank": 22,
                "firstname": "Nadine",
                "lastname": "Ruh",
                "paraclimbing_sport_class": null,
                "sport_class_status": null,
                "country": "GER",
                "federation_id": 6,
                "rounds": []
            },
            {
                "athlete_id": 5505,
                "rank": 23,
                "firstname": "Gabriela",
                "lastname": "Dobrota",
                "paraclimbing_sport_class": null,
                "sport_class_status": null,
                "country": "SRB",
                "federation_id": 56,
                "rounds": []
            },
            {
                "athlete_id": 2420,
                "rank": 24,
                "firstname": "Petya",
                "lastname": "Garbova",
                "paraclimbing_sport_class": null,
                "sport_class_status": null,
                "country": "BUL",
                "federation_id": 26,
                "rounds": []
            },
            {
                "athlete_id": 5506,
                "rank": 25,
                "firstname": "Plamena",
                "lastname": "Bakalova",
                "paraclimbing_sport_class": null,
                "sport_class_status": null,
                "country": "BUL",
                "federation_id": 26,
                "rounds": []
            },
            {
                "athlete_id": 5507,
                "rank": 26,
                "firstname": "Cveta",
                "lastname": "Kojuharova",
                "paraclimbing_sport_class": null,
                "sport_class_status": null,
                "country": "BUL",
                "federation_id": 26,
                "rounds": []
            },
            {
                "athlete_id": 5508,
                "rank": 27,
                "firstname": "Siyana",
                "lastname": "Kyutinska",
                "paraclimbing_sport_class": null,
                "sport_class_status": null,
                "country": "BUL",
                "federation_id": 26,
                "rounds": []
            }
        ],
        "SPEED Men": [
            {
                "athlete_id": 56,
                "rank": 1,
                "firstname": "Evgenii",
                "lastname": "Vaitsekhovskii",
                "paraclimbing_sport_class": null,
                "sport_class_status": null,
                "country": "RUS",
                "federation_id": 7,
                "rounds": []
            },
            {
                "athlete_id": 52,
                "rank": 2,
                "firstname": "Alexander",
                "lastname": "Peshekhonov",
                "paraclimbing_sport_class": null,
                "sport_class_status": null,
                "country": "RUS",
                "federation_id": 7,
                "rounds": []
            },
            {
                "athlete_id": 48,
                "rank": 3,
                "firstname": "Sergei",
                "lastname": "Sinitcyn",
                "paraclimbing_sport_class": null,
                "sport_class_status": null,
                "country": "RUS",
                "federation_id": 7,
                "rounds": []
            },
            {
                "athlete_id": 1470,
                "rank": 4,
                "firstname": "Maksym",
                "lastname": "Styenkovyy",
                "paraclimbing_sport_class": null,
                "sport_class_status": null,
                "country": "UKR",
                "federation_id": 18,
                "rounds": []
            },
            {
                "athlete_id": 4581,
                "rank": 5,
                "firstname": "Tomasz",
                "lastname": "Oleksy",
                "paraclimbing_sport_class": null,
                "sport_class_status": null,
                "country": "POL",
                "federation_id": 36,
                "rounds": []
            },
            {
                "athlete_id": 4631,
                "rank": 6,
                "firstname": "Iakov",
                "lastname": "Soubbotine",
                "paraclimbing_sport_class": null,
                "sport_class_status": null,
                "country": "RUS",
                "federation_id": 7,
                "rounds": []
            },
            {
                "athlete_id": 5010,
                "rank": 7,
                "firstname": "Chi-Wai",
                "lastname": "Lai",
                "paraclimbing_sport_class": null,
                "sport_class_status": null,
                "country": "HKG",
                "federation_id": 24,
                "rounds": []
            },
            {
                "athlete_id": 2167,
                "rank": 8,
                "firstname": "Csaba",
                "lastname": "Komondi",
                "paraclimbing_sport_class": null,
                "sport_class_status": null,
                "country": "HUN",
                "federation_id": 23,
                "rounds": []
            },
            {
                "athlete_id": 4630,
                "rank": 9,
                "firstname": "Alexandre",
                "lastname": "Chaoulsky",
                "paraclimbing_sport_class": null,
                "sport_class_status": null,
                "country": "RUS",
                "federation_id": 7,
                "rounds": []
            },
            {
                "athlete_id": 51,
                "rank": 10,
                "firstname": "Alexander",
                "lastname": "Kosterin",
                "paraclimbing_sport_class": null,
                "sport_class_status": null,
                "country": "RUS",
                "federation_id": 7,
                "rounds": []
            },
            {
                "athlete_id": 1359,
                "rank": 11,
                "firstname": "Libor",
                "lastname": "Hroza",
                "paraclimbing_sport_class": null,
                "sport_class_status": null,
                "country": "CZE",
                "federation_id": 17,
                "rounds": []
            },
            {
                "athlete_id": 5513,
                "rank": 12,
                "firstname": "Oleksandr",
                "lastname": "Lakhin",
                "paraclimbing_sport_class": null,
                "sport_class_status": null,
                "country": "UKR",
                "federation_id": 18,
                "rounds": []
            },
            {
                "athlete_id": 2416,
                "rank": 13,
                "firstname": "Kalin",
                "lastname": "Garbov",
                "paraclimbing_sport_class": null,
                "sport_class_status": null,
                "country": "BUL",
                "federation_id": 26,
                "rounds": []
            },
            {
                "athlete_id": 53,
                "rank": 14,
                "firstname": "Dmitrii",
                "lastname": "Sharafutdinov",
                "paraclimbing_sport_class": null,
                "sport_class_status": null,
                "country": "RUS",
                "federation_id": 7,
                "rounds": []
            },
            {
                "athlete_id": 2417,
                "rank": 15,
                "firstname": "Milen",
                "lastname": "Videnovski",
                "paraclimbing_sport_class": null,
                "sport_class_status": null,
                "country": "BUL",
                "federation_id": 26,
                "rounds": []
            },
            {
                "athlete_id": 5169,
                "rank": 16,
                "firstname": "Marat",
                "lastname": "Sadyrov",
                "paraclimbing_sport_class": null,
                "sport_class_status": null,
                "country": "RUS",
                "federation_id": 7,
                "rounds": []
            },
            {
                "athlete_id": 5181,
                "rank": 17,
                "firstname": "Ivan",
                "lastname": "Shyshkovskyy",
                "paraclimbing_sport_class": null,
                "sport_class_status": null,
                "country": "UKR",
                "federation_id": 18,
                "rounds": []
            },
            {
                "athlete_id": 4864,
                "rank": 18,
                "firstname": "Ivan",
                "lastname": "Kaurov",
                "paraclimbing_sport_class": null,
                "sport_class_status": null,
                "country": "RUS",
                "federation_id": 7,
                "rounds": []
            },
            {
                "athlete_id": 5237,
                "rank": 19,
                "firstname": "Janmin",
                "lastname": "Wang",
                "paraclimbing_sport_class": null,
                "sport_class_status": null,
                "country": "CHN",
                "federation_id": 37,
                "rounds": []
            },
            {
                "athlete_id": 4819,
                "rank": 20,
                "firstname": "Blagovest",
                "lastname": "Lazarov",
                "paraclimbing_sport_class": null,
                "sport_class_status": null,
                "country": "BUL",
                "federation_id": 26,
                "rounds": []
            },
            {
                "athlete_id": 4826,
                "rank": 21,
                "firstname": "Stefan",
                "lastname": "Avramov",
                "paraclimbing_sport_class": null,
                "sport_class_status": null,
                "country": "BUL",
                "federation_id": 26,
                "rounds": []
            },
            {
                "athlete_id": 4753,
                "rank": 22,
                "firstname": "Salah",
                "lastname": "Boulbahaiem",
                "paraclimbing_sport_class": null,
                "sport_class_status": null,
                "country": "BEL",
                "federation_id": 9,
                "rounds": []
            }
        ],
        "SPEED Women": [
            {
                "athlete_id": 46,
                "rank": 1,
                "firstname": "Anna",
                "lastname": "Stenkovaya",
                "paraclimbing_sport_class": null,
                "sport_class_status": null,
                "country": "RUS",
                "federation_id": 7,
                "rounds": []
            },
            {
                "athlete_id": 45,
                "rank": 2,
                "firstname": "Valentina",
                "lastname": "Yurina",
                "paraclimbing_sport_class": null,
                "sport_class_status": null,
                "country": "RUS",
                "federation_id": 7,
                "rounds": []
            },
            {
                "athlete_id": 42,
                "rank": 3,
                "firstname": "Tatiana",
                "lastname": "Ruyga",
                "paraclimbing_sport_class": null,
                "sport_class_status": null,
                "country": "RUS",
                "federation_id": 7,
                "rounds": []
            },
            {
                "athlete_id": 4736,
                "rank": 4,
                "firstname": "Olga",
                "lastname": "Evstigneeva",
                "paraclimbing_sport_class": null,
                "sport_class_status": null,
                "country": "RUS",
                "federation_id": 7,
                "rounds": []
            },
            {
                "athlete_id": 5548,
                "rank": 5,
                "firstname": "Agung Ethi",
                "lastname": "Hendrawati",
                "paraclimbing_sport_class": null,
                "sport_class_status": null,
                "country": "INA",
                "federation_id": 45,
                "rounds": []
            },
            {
                "athlete_id": 3257,
                "rank": 6,
                "firstname": "Evi",
                "lastname": "Neliwati",
                "paraclimbing_sport_class": null,
                "sport_class_status": null,
                "country": "INA",
                "federation_id": 45,
                "rounds": []
            },
            {
                "athlete_id": 1474,
                "rank": 7,
                "firstname": "Svitlana",
                "lastname": "Tuzhylina",
                "paraclimbing_sport_class": null,
                "sport_class_status": null,
                "country": "UKR",
                "federation_id": 18,
                "rounds": []
            },
            {
                "athlete_id": 5420,
                "rank": 8,
                "firstname": "Eliska",
                "lastname": "Karesova",
                "paraclimbing_sport_class": null,
                "sport_class_status": null,
                "country": "CZE",
                "federation_id": 17,
                "rounds": []
            },
            {
                "athlete_id": 5110,
                "rank": 9,
                "firstname": "Olesya",
                "lastname": "Saulevich",
                "paraclimbing_sport_class": null,
                "sport_class_status": null,
                "country": "RUS",
                "federation_id": 7,
                "rounds": []
            },
            {
                "athlete_id": 5506,
                "rank": 10,
                "firstname": "Plamena",
                "lastname": "Bakalova",
                "paraclimbing_sport_class": null,
                "sport_class_status": null,
                "country": "BUL",
                "federation_id": 26,
                "rounds": []
            },
            {
                "athlete_id": 2420,
                "rank": 11,
                "firstname": "Petya",
                "lastname": "Garbova",
                "paraclimbing_sport_class": null,
                "sport_class_status": null,
                "country": "BUL",
                "federation_id": 26,
                "rounds": []
            },
            {
                "athlete_id": 5509,
                "rank": 12,
                "firstname": "Radiana",
                "lastname": "Maneva",
                "paraclimbing_sport_class": null,
                "sport_class_status": null,
                "country": "BUL",
                "federation_id": 26,
                "rounds": []
            },
            {
                "athlete_id": 4573,
                "rank": 13,
                "firstname": "Olga",
                "lastname": "Zakharova",
                "paraclimbing_sport_class": null,
                "sport_class_status": null,
                "country": "UKR",
                "federation_id": 18,
                "rounds": []
            }
        ]
    },
    "event_videos": [
        {
            "event_name": "LEAD Men",
            "original_url": "",
            "ipfs_cid": ""
        },
        {
            "event_name": "LEAD Women",
            "original_url": "",
            "ipfs_cid": ""
        },
        {
            "event_name": "SPEED Men",
            "original_url": "",
            "ipfs_cid": ""
        },
        {
            "event_name": "SPEED Women",
            "original_url": "",
            "ipfs_cid": ""
        }
    ]
}