{
    "id": 440,
    "name": "UIAA Climbing Worldcup (B+S) - Moscow (RUS) 2006",
    "league_id": 1,
    "league_season_id": 220,
    "season_id": 19,
    "starts_at": "2006-11-02 00:00:00 UTC",
    "ends_at": "2006-11-04 00:00:00 UTC",
    "local_start_date": "2006-11-02",
    "local_end_date": "2006-11-04",
    "timezone": null,
    "location": "Moscow (B+S)",
    "public_information": {
        "organiser_name": null,
        "organiser_url": null,
        "venue_name": null
    },
    "computed_combined_categories": [],
    "team_ranking_disciplines": [
        "boulder",
        "speed"
    ],
    "team_ranking_url": "/api/v1/events/440/team_results/",
    "categories": [
        "BOULDER Men",
        "BOULDER Women",
        "SPEED Men",
        "SPEED Women"
    ],
    "results": {
        "BOULDER Men": [
            {
                "athlete_id": 1204,
                "rank": 1,
                "firstname": "Kilian",
                "lastname": "Fischhuber",
                "paraclimbing_sport_class": null,
                "sport_class_status": null,
                "country": "AUT",
                "federation_id": 16,
                "rounds": []
            },
            {
                "athlete_id": 4465,
                "rank": 2,
                "firstname": "Salavat",
                "lastname": "Rakhmetov",
                "paraclimbing_sport_class": null,
                "sport_class_status": null,
                "country": "RUS",
                "federation_id": 7,
                "rounds": []
            },
            {
                "athlete_id": 4581,
                "rank": 3,
                "firstname": "Tomasz",
                "lastname": "Oleksy",
                "paraclimbing_sport_class": null,
                "sport_class_status": null,
                "country": "POL",
                "federation_id": 36,
                "rounds": []
            },
            {
                "athlete_id": 3576,
                "rank": 4,
                "firstname": "Wouter",
                "lastname": "Jongeneelen",
                "paraclimbing_sport_class": null,
                "sport_class_status": null,
                "country": "NED",
                "federation_id": 50,
                "rounds": []
            },
            {
                "athlete_id": 1356,
                "rank": 5,
                "firstname": "Tom\u00e1s",
                "lastname": "Mr\u00e1zek",
                "paraclimbing_sport_class": null,
                "sport_class_status": null,
                "country": "CZE",
                "federation_id": 17,
                "rounds": []
            },
            {
                "athlete_id": 4463,
                "rank": 6,
                "firstname": "Christian",
                "lastname": "Core",
                "paraclimbing_sport_class": null,
                "sport_class_status": null,
                "country": "ITA",
                "federation_id": 13,
                "rounds": []
            },
            {
                "athlete_id": 53,
                "rank": 7,
                "firstname": "Dmitrii",
                "lastname": "Sharafutdinov",
                "paraclimbing_sport_class": null,
                "sport_class_status": null,
                "country": "RUS",
                "federation_id": 7,
                "rounds": []
            },
            {
                "athlete_id": 412,
                "rank": 8,
                "firstname": "J\u00e9r\u00f4me",
                "lastname": "Meyer",
                "paraclimbing_sport_class": null,
                "sport_class_status": null,
                "country": "FRA",
                "federation_id": 10,
                "rounds": []
            },
            {
                "athlete_id": 5292,
                "rank": 9,
                "firstname": "Nicolas",
                "lastname": "Badia",
                "paraclimbing_sport_class": null,
                "sport_class_status": null,
                "country": "FRA",
                "federation_id": 10,
                "rounds": []
            },
            {
                "athlete_id": 425,
                "rank": 10,
                "firstname": "Stephane",
                "lastname": "Julien",
                "paraclimbing_sport_class": null,
                "sport_class_status": null,
                "country": "FRA",
                "federation_id": 10,
                "rounds": []
            },
            {
                "athlete_id": 61,
                "rank": 11,
                "firstname": "Mikhail",
                "lastname": "Chernikov",
                "paraclimbing_sport_class": null,
                "sport_class_status": null,
                "country": "RUS",
                "federation_id": 7,
                "rounds": []
            },
            {
                "athlete_id": 2822,
                "rank": 12,
                "firstname": "Jonas",
                "lastname": "Baumann",
                "paraclimbing_sport_class": null,
                "sport_class_status": null,
                "country": "GER",
                "federation_id": 6,
                "rounds": []
            },
            {
                "athlete_id": 4776,
                "rank": 13,
                "firstname": "Mykhaylo",
                "lastname": "Shalagin",
                "paraclimbing_sport_class": null,
                "sport_class_status": null,
                "country": "UKR",
                "federation_id": 18,
                "rounds": []
            },
            {
                "athlete_id": 5140,
                "rank": 14,
                "firstname": "Andrew",
                "lastname": "Earl",
                "paraclimbing_sport_class": null,
                "sport_class_status": null,
                "country": "GBR",
                "federation_id": 11,
                "rounds": []
            },
            {
                "athlete_id": 5278,
                "rank": 15,
                "firstname": "Mikhail",
                "lastname": "Pekarev",
                "paraclimbing_sport_class": null,
                "sport_class_status": null,
                "country": "RUS",
                "federation_id": 7,
                "rounds": []
            },
            {
                "athlete_id": 4773,
                "rank": 16,
                "firstname": "Lo\u00efc",
                "lastname": "Gaidioz",
                "paraclimbing_sport_class": null,
                "sport_class_status": null,
                "country": "FRA",
                "federation_id": 10,
                "rounds": []
            },
            {
                "athlete_id": 4788,
                "rank": 17,
                "firstname": "Stanislav",
                "lastname": "Kleshnov",
                "paraclimbing_sport_class": null,
                "sport_class_status": null,
                "country": "UKR",
                "federation_id": 18,
                "rounds": []
            },
            {
                "athlete_id": 4905,
                "rank": 18,
                "firstname": "Gareth",
                "lastname": "Parry",
                "paraclimbing_sport_class": null,
                "sport_class_status": null,
                "country": "GBR",
                "federation_id": 11,
                "rounds": []
            },
            {
                "athlete_id": 4609,
                "rank": 19,
                "firstname": "Ferdinand",
                "lastname": "Schulte",
                "paraclimbing_sport_class": null,
                "sport_class_status": null,
                "country": "NED",
                "federation_id": 50,
                "rounds": []
            },
            {
                "athlete_id": 5334,
                "rank": 20,
                "firstname": "Rok",
                "lastname": "Klancnik",
                "paraclimbing_sport_class": null,
                "sport_class_status": null,
                "country": "SLO",
                "federation_id": 15,
                "rounds": []
            },
            {
                "athlete_id": 1116,
                "rank": 21,
                "firstname": "Urh",
                "lastname": "Cehovin",
                "paraclimbing_sport_class": null,
                "sport_class_status": null,
                "country": "SLO",
                "federation_id": 15,
                "rounds": []
            },
            {
                "athlete_id": 634,
                "rank": 22,
                "firstname": "David",
                "lastname": "Barrans",
                "paraclimbing_sport_class": null,
                "sport_class_status": null,
                "country": "GBR",
                "federation_id": 11,
                "rounds": []
            },
            {
                "athlete_id": 4864,
                "rank": 23,
                "firstname": "Ivan",
                "lastname": "Kaurov",
                "paraclimbing_sport_class": null,
                "sport_class_status": null,
                "country": "RUS",
                "federation_id": 7,
                "rounds": []
            },
            {
                "athlete_id": 4726,
                "rank": 24,
                "firstname": "Matthias",
                "lastname": "M\u00fcller",
                "paraclimbing_sport_class": null,
                "sport_class_status": null,
                "country": "SUI",
                "federation_id": 8,
                "rounds": []
            },
            {
                "athlete_id": 5265,
                "rank": 25,
                "firstname": "Andre",
                "lastname": "Borowka",
                "paraclimbing_sport_class": null,
                "sport_class_status": null,
                "country": "GER",
                "federation_id": 6,
                "rounds": []
            },
            {
                "athlete_id": 4907,
                "rank": 26,
                "firstname": "Mark",
                "lastname": "Croxall",
                "paraclimbing_sport_class": null,
                "sport_class_status": null,
                "country": "GBR",
                "federation_id": 11,
                "rounds": []
            },
            {
                "athlete_id": 5736,
                "rank": 27,
                "firstname": "Andrey",
                "lastname": "Ladniy",
                "paraclimbing_sport_class": null,
                "sport_class_status": null,
                "country": "RUS",
                "federation_id": 7,
                "rounds": []
            },
            {
                "athlete_id": 47,
                "rank": 28,
                "firstname": "Vasily",
                "lastname": "Kozlov",
                "paraclimbing_sport_class": null,
                "sport_class_status": null,
                "country": "RUS",
                "federation_id": 7,
                "rounds": []
            },
            {
                "athlete_id": 4865,
                "rank": 29,
                "firstname": "Sergei",
                "lastname": "Shaferov",
                "paraclimbing_sport_class": null,
                "sport_class_status": null,
                "country": "BLR",
                "federation_id": 48,
                "rounds": []
            },
            {
                "athlete_id": 5737,
                "rank": 30,
                "firstname": "Kirill",
                "lastname": "D'yakonov",
                "paraclimbing_sport_class": null,
                "sport_class_status": null,
                "country": "RUS",
                "federation_id": 7,
                "rounds": []
            },
            {
                "athlete_id": 5673,
                "rank": 31,
                "firstname": "Tom",
                "lastname": "Gore",
                "paraclimbing_sport_class": null,
                "sport_class_status": null,
                "country": "GBR",
                "federation_id": 11,
                "rounds": []
            },
            {
                "athlete_id": 60,
                "rank": 32,
                "firstname": "Rustam",
                "lastname": "Gelmanov",
                "paraclimbing_sport_class": null,
                "sport_class_status": null,
                "country": "RUS",
                "federation_id": 7,
                "rounds": []
            },
            {
                "athlete_id": 1467,
                "rank": 33,
                "firstname": "Serik",
                "lastname": "Kazbekov",
                "paraclimbing_sport_class": null,
                "sport_class_status": null,
                "country": "UKR",
                "federation_id": 18,
                "rounds": []
            },
            {
                "athlete_id": 5738,
                "rank": 34,
                "firstname": "Pavel",
                "lastname": "Peskin",
                "paraclimbing_sport_class": null,
                "sport_class_status": null,
                "country": "RUS",
                "federation_id": 7,
                "rounds": []
            },
            {
                "athlete_id": 5163,
                "rank": 34,
                "firstname": "Alexei",
                "lastname": "Zemski",
                "paraclimbing_sport_class": null,
                "sport_class_status": null,
                "country": "RUS",
                "federation_id": 7,
                "rounds": []
            },
            {
                "athlete_id": 59,
                "rank": 36,
                "firstname": "Alexander",
                "lastname": "Stepanov",
                "paraclimbing_sport_class": null,
                "sport_class_status": null,
                "country": "RUS",
                "federation_id": 7,
                "rounds": []
            },
            {
                "athlete_id": 5739,
                "rank": 37,
                "firstname": "Ilya",
                "lastname": "Kazennov",
                "paraclimbing_sport_class": null,
                "sport_class_status": null,
                "country": "RUS",
                "federation_id": 7,
                "rounds": []
            },
            {
                "athlete_id": 5497,
                "rank": 38,
                "firstname": "Aleksei",
                "lastname": "Portsev",
                "paraclimbing_sport_class": null,
                "sport_class_status": null,
                "country": "RUS",
                "federation_id": 7,
                "rounds": []
            },
            {
                "athlete_id": 5740,
                "rank": 39,
                "firstname": "Vladimir",
                "lastname": "Murzaev",
                "paraclimbing_sport_class": null,
                "sport_class_status": null,
                "country": "RUS",
                "federation_id": 7,
                "rounds": []
            },
            {
                "athlete_id": 5175,
                "rank": 40,
                "firstname": "Alexander",
                "lastname": "Khopko",
                "paraclimbing_sport_class": null,
                "sport_class_status": null,
                "country": "RUS",
                "federation_id": 7,
                "rounds": []
            },
            {
                "athlete_id": 4938,
                "rank": 40,
                "firstname": "Stanislav",
                "lastname": "Poplavskiy",
                "paraclimbing_sport_class": null,
                "sport_class_status": null,
                "country": "RUS",
                "federation_id": 7,
                "rounds": []
            },
            {
                "athlete_id": 5495,
                "rank": 42,
                "firstname": "Dmitriy",
                "lastname": "Portsev",
                "paraclimbing_sport_class": null,
                "sport_class_status": null,
                "country": "RUS",
                "federation_id": 7,
                "rounds": []
            },
            {
                "athlete_id": 1479,
                "rank": 43,
                "firstname": "Sergii",
                "lastname": "Karpin",
                "paraclimbing_sport_class": null,
                "sport_class_status": null,
                "country": "UKR",
                "federation_id": 18,
                "rounds": []
            },
            {
                "athlete_id": 5741,
                "rank": 43,
                "firstname": "Vasilii",
                "lastname": "Kursin",
                "paraclimbing_sport_class": null,
                "sport_class_status": null,
                "country": "RUS",
                "federation_id": 7,
                "rounds": []
            },
            {
                "athlete_id": 5369,
                "rank": 45,
                "firstname": "Henrik",
                "lastname": "Sennel\u00f6v",
                "paraclimbing_sport_class": null,
                "sport_class_status": null,
                "country": "SWE",
                "federation_id": 32,
                "rounds": []
            },
            {
                "athlete_id": 5272,
                "rank": 46,
                "firstname": "Kyrylo",
                "lastname": "Shevchenko",
                "paraclimbing_sport_class": null,
                "sport_class_status": null,
                "country": "UKR",
                "federation_id": 18,
                "rounds": []
            },
            {
                "athlete_id": 4874,
                "rank": 47,
                "firstname": "Denis",
                "lastname": "Zhendinskiy",
                "paraclimbing_sport_class": null,
                "sport_class_status": null,
                "country": "KAZ",
                "federation_id": 47,
                "rounds": []
            }
        ],
        "BOULDER Women": [
            {
                "athlete_id": 43,
                "rank": 1,
                "firstname": "Yulia",
                "lastname": "Abramchuk",
                "paraclimbing_sport_class": null,
                "sport_class_status": null,
                "country": "RUS",
                "federation_id": 7,
                "rounds": []
            },
            {
                "athlete_id": 4756,
                "rank": 2,
                "firstname": "Olga",
                "lastname": "Shalagina",
                "paraclimbing_sport_class": null,
                "sport_class_status": null,
                "country": "UKR",
                "federation_id": 18,
                "rounds": []
            },
            {
                "athlete_id": 1119,
                "rank": 3,
                "firstname": "Natalija",
                "lastname": "Gros",
                "paraclimbing_sport_class": null,
                "sport_class_status": null,
                "country": "SLO",
                "federation_id": 15,
                "rounds": []
            },
            {
                "athlete_id": 41,
                "rank": 4,
                "firstname": "Olga",
                "lastname": "Bibik",
                "paraclimbing_sport_class": null,
                "sport_class_status": null,
                "country": "RUS",
                "federation_id": 7,
                "rounds": []
            },
            {
                "athlete_id": 4757,
                "rank": 5,
                "firstname": "Maud",
                "lastname": "Ansade",
                "paraclimbing_sport_class": null,
                "sport_class_status": null,
                "country": "FRA",
                "federation_id": 10,
                "rounds": []
            },
            {
                "athlete_id": 58,
                "rank": 6,
                "firstname": "Yana",
                "lastname": "Chereshneva",
                "paraclimbing_sport_class": null,
                "sport_class_status": null,
                "country": "RUS",
                "federation_id": 7,
                "rounds": []
            },
            {
                "athlete_id": 1474,
                "rank": 7,
                "firstname": "Svitlana",
                "lastname": "Tuzhylina",
                "paraclimbing_sport_class": null,
                "sport_class_status": null,
                "country": "UKR",
                "federation_id": 18,
                "rounds": []
            },
            {
                "athlete_id": 5493,
                "rank": 8,
                "firstname": "Olga",
                "lastname": "Bezhko",
                "paraclimbing_sport_class": null,
                "sport_class_status": null,
                "country": "UKR",
                "federation_id": 18,
                "rounds": []
            },
            {
                "athlete_id": 4735,
                "rank": 9,
                "firstname": "Kseniia",
                "lastname": "Alekseeva",
                "paraclimbing_sport_class": null,
                "sport_class_status": null,
                "country": "RUS",
                "federation_id": 7,
                "rounds": []
            },
            {
                "athlete_id": 1120,
                "rank": 10,
                "firstname": "Katja",
                "lastname": "Vidmar",
                "paraclimbing_sport_class": null,
                "sport_class_status": null,
                "country": "SLO",
                "federation_id": 15,
                "rounds": []
            },
            {
                "athlete_id": 1211,
                "rank": 11,
                "firstname": "Anna",
                "lastname": "St\u00f6hr",
                "paraclimbing_sport_class": null,
                "sport_class_status": null,
                "country": "AUT",
                "federation_id": 16,
                "rounds": []
            },
            {
                "athlete_id": 50,
                "rank": 12,
                "firstname": "Tatiana",
                "lastname": "Shemulinkina ",
                "paraclimbing_sport_class": null,
                "sport_class_status": null,
                "country": "RUS",
                "federation_id": 7,
                "rounds": []
            },
            {
                "athlete_id": 1202,
                "rank": 13,
                "firstname": "Barbara",
                "lastname": "Bacher",
                "paraclimbing_sport_class": null,
                "sport_class_status": null,
                "country": "AUT",
                "federation_id": 16,
                "rounds": []
            },
            {
                "athlete_id": 309,
                "rank": 14,
                "firstname": "Chlo\u00e9",
                "lastname": "Graftiaux",
                "paraclimbing_sport_class": null,
                "sport_class_status": null,
                "country": "BEL",
                "federation_id": 9,
                "rounds": []
            },
            {
                "athlete_id": 1360,
                "rank": 15,
                "firstname": "Silvie",
                "lastname": "Rajfova",
                "paraclimbing_sport_class": null,
                "sport_class_status": null,
                "country": "CZE",
                "federation_id": 17,
                "rounds": []
            },
            {
                "athlete_id": 1469,
                "rank": 16,
                "firstname": "Nataliya",
                "lastname": "Perlova",
                "paraclimbing_sport_class": null,
                "sport_class_status": null,
                "country": "UKR",
                "federation_id": 18,
                "rounds": []
            },
            {
                "athlete_id": 1358,
                "rank": 17,
                "firstname": "Helena",
                "lastname": "Lipenska",
                "paraclimbing_sport_class": null,
                "sport_class_status": null,
                "country": "CZE",
                "federation_id": 17,
                "rounds": []
            },
            {
                "athlete_id": 4761,
                "rank": 18,
                "firstname": "Anna",
                "lastname": "Gallyamova",
                "paraclimbing_sport_class": null,
                "sport_class_status": null,
                "country": "RUS",
                "federation_id": 7,
                "rounds": []
            },
            {
                "athlete_id": 5733,
                "rank": 19,
                "firstname": "Maria",
                "lastname": "Agafonova",
                "paraclimbing_sport_class": null,
                "sport_class_status": null,
                "country": "RUS",
                "federation_id": 7,
                "rounds": []
            },
            {
                "athlete_id": 4758,
                "rank": 20,
                "firstname": "Alexandra",
                "lastname": "Balakireva",
                "paraclimbing_sport_class": null,
                "sport_class_status": null,
                "country": "RUS",
                "federation_id": 7,
                "rounds": []
            },
            {
                "athlete_id": 2664,
                "rank": 21,
                "firstname": "Angelica",
                "lastname": "Lind",
                "paraclimbing_sport_class": null,
                "sport_class_status": null,
                "country": "SWE",
                "federation_id": 32,
                "rounds": []
            },
            {
                "athlete_id": 5044,
                "rank": 22,
                "firstname": "M\u00e9lanie",
                "lastname": "Son",
                "paraclimbing_sport_class": null,
                "sport_class_status": null,
                "country": "FRA",
                "federation_id": 10,
                "rounds": []
            },
            {
                "athlete_id": 5426,
                "rank": 23,
                "firstname": "Anja",
                "lastname": "Hodann",
                "paraclimbing_sport_class": null,
                "sport_class_status": null,
                "country": "SWE",
                "federation_id": 32,
                "rounds": []
            },
            {
                "athlete_id": 5630,
                "rank": 24,
                "firstname": "Audrey",
                "lastname": "Seguy",
                "paraclimbing_sport_class": null,
                "sport_class_status": null,
                "country": "GBR",
                "federation_id": 11,
                "rounds": []
            },
            {
                "athlete_id": 3578,
                "rank": 25,
                "firstname": "Vera",
                "lastname": "Zijlstra",
                "paraclimbing_sport_class": null,
                "sport_class_status": null,
                "country": "NED",
                "federation_id": 50,
                "rounds": []
            },
            {
                "athlete_id": 5280,
                "rank": 26,
                "firstname": "Juliette",
                "lastname": "Danion",
                "paraclimbing_sport_class": null,
                "sport_class_status": null,
                "country": "FRA",
                "federation_id": 10,
                "rounds": []
            },
            {
                "athlete_id": 5040,
                "rank": 27,
                "firstname": "Emilie",
                "lastname": "Abgrall",
                "paraclimbing_sport_class": null,
                "sport_class_status": null,
                "country": "FRA",
                "federation_id": 10,
                "rounds": []
            },
            {
                "athlete_id": 5734,
                "rank": 28,
                "firstname": "Valeriya",
                "lastname": "Leshchenko",
                "paraclimbing_sport_class": null,
                "sport_class_status": null,
                "country": "UKR",
                "federation_id": 18,
                "rounds": []
            }
        ],
        "SPEED Men": [
            {
                "athlete_id": 3174,
                "rank": 1,
                "firstname": "Manuel",
                "lastname": "Escobar",
                "paraclimbing_sport_class": null,
                "sport_class_status": null,
                "country": "VEN",
                "federation_id": 42,
                "rounds": []
            },
            {
                "athlete_id": 48,
                "rank": 2,
                "firstname": "Sergei",
                "lastname": "Sinitcyn",
                "paraclimbing_sport_class": null,
                "sport_class_status": null,
                "country": "RUS",
                "federation_id": 7,
                "rounds": []
            },
            {
                "athlete_id": 1471,
                "rank": 3,
                "firstname": "Oleksandr",
                "lastname": "Salimov",
                "paraclimbing_sport_class": null,
                "sport_class_status": null,
                "country": "UKR",
                "federation_id": 18,
                "rounds": []
            },
            {
                "athlete_id": 5742,
                "rank": 4,
                "firstname": "Eduard",
                "lastname": "Ismagilov",
                "paraclimbing_sport_class": null,
                "sport_class_status": null,
                "country": "RUS",
                "federation_id": 7,
                "rounds": []
            },
            {
                "athlete_id": 5169,
                "rank": 5,
                "firstname": "Marat",
                "lastname": "Sadyrov",
                "paraclimbing_sport_class": null,
                "sport_class_status": null,
                "country": "RUS",
                "federation_id": 7,
                "rounds": []
            },
            {
                "athlete_id": 4885,
                "rank": 6,
                "firstname": "Valeriy",
                "lastname": "Vorobyev",
                "paraclimbing_sport_class": null,
                "sport_class_status": null,
                "country": "RUS",
                "federation_id": 7,
                "rounds": []
            },
            {
                "athlete_id": 54,
                "rank": 7,
                "firstname": "Anatoly",
                "lastname": "Skripov",
                "paraclimbing_sport_class": null,
                "sport_class_status": null,
                "country": "RUS",
                "federation_id": 7,
                "rounds": []
            },
            {
                "athlete_id": 52,
                "rank": 8,
                "firstname": "Alexander",
                "lastname": "Peshekhonov",
                "paraclimbing_sport_class": null,
                "sport_class_status": null,
                "country": "RUS",
                "federation_id": 7,
                "rounds": []
            },
            {
                "athlete_id": 53,
                "rank": 9,
                "firstname": "Dmitrii",
                "lastname": "Sharafutdinov",
                "paraclimbing_sport_class": null,
                "sport_class_status": null,
                "country": "RUS",
                "federation_id": 7,
                "rounds": []
            },
            {
                "athlete_id": 4581,
                "rank": 10,
                "firstname": "Tomasz",
                "lastname": "Oleksy",
                "paraclimbing_sport_class": null,
                "sport_class_status": null,
                "country": "POL",
                "federation_id": 36,
                "rounds": []
            },
            {
                "athlete_id": 47,
                "rank": 11,
                "firstname": "Vasily",
                "lastname": "Kozlov",
                "paraclimbing_sport_class": null,
                "sport_class_status": null,
                "country": "RUS",
                "federation_id": 7,
                "rounds": []
            },
            {
                "athlete_id": 5741,
                "rank": 12,
                "firstname": "Vasilii",
                "lastname": "Kursin",
                "paraclimbing_sport_class": null,
                "sport_class_status": null,
                "country": "RUS",
                "federation_id": 7,
                "rounds": []
            },
            {
                "athlete_id": 433,
                "rank": 13,
                "firstname": "Sylvain",
                "lastname": "Chapelle",
                "paraclimbing_sport_class": null,
                "sport_class_status": null,
                "country": "FRA",
                "federation_id": 10,
                "rounds": []
            },
            {
                "athlete_id": 5497,
                "rank": 14,
                "firstname": "Aleksei",
                "lastname": "Portsev",
                "paraclimbing_sport_class": null,
                "sport_class_status": null,
                "country": "RUS",
                "federation_id": 7,
                "rounds": []
            },
            {
                "athlete_id": 5605,
                "rank": 15,
                "firstname": "Nestor",
                "lastname": "Carvajal",
                "paraclimbing_sport_class": null,
                "sport_class_status": null,
                "country": "VEN",
                "federation_id": 42,
                "rounds": []
            },
            {
                "athlete_id": 5175,
                "rank": 16,
                "firstname": "Alexander",
                "lastname": "Khopko",
                "paraclimbing_sport_class": null,
                "sport_class_status": null,
                "country": "RUS",
                "federation_id": 7,
                "rounds": []
            },
            {
                "athlete_id": 5743,
                "rank": 17,
                "firstname": "Stanislav",
                "lastname": "Shmatko",
                "paraclimbing_sport_class": null,
                "sport_class_status": null,
                "country": "RUS",
                "federation_id": 7,
                "rounds": []
            },
            {
                "athlete_id": 4864,
                "rank": 18,
                "firstname": "Ivan",
                "lastname": "Kaurov",
                "paraclimbing_sport_class": null,
                "sport_class_status": null,
                "country": "RUS",
                "federation_id": 7,
                "rounds": []
            },
            {
                "athlete_id": 2822,
                "rank": 19,
                "firstname": "Jonas",
                "lastname": "Baumann",
                "paraclimbing_sport_class": null,
                "sport_class_status": null,
                "country": "GER",
                "federation_id": 6,
                "rounds": []
            },
            {
                "athlete_id": 61,
                "rank": 20,
                "firstname": "Mikhail",
                "lastname": "Chernikov",
                "paraclimbing_sport_class": null,
                "sport_class_status": null,
                "country": "RUS",
                "federation_id": 7,
                "rounds": []
            },
            {
                "athlete_id": 59,
                "rank": 21,
                "firstname": "Alexander",
                "lastname": "Stepanov",
                "paraclimbing_sport_class": null,
                "sport_class_status": null,
                "country": "RUS",
                "federation_id": 7,
                "rounds": []
            },
            {
                "athlete_id": 4938,
                "rank": 22,
                "firstname": "Stanislav",
                "lastname": "Poplavskiy",
                "paraclimbing_sport_class": null,
                "sport_class_status": null,
                "country": "RUS",
                "federation_id": 7,
                "rounds": []
            },
            {
                "athlete_id": 5163,
                "rank": 23,
                "firstname": "Alexei",
                "lastname": "Zemski",
                "paraclimbing_sport_class": null,
                "sport_class_status": null,
                "country": "RUS",
                "federation_id": 7,
                "rounds": []
            },
            {
                "athlete_id": 5495,
                "rank": 24,
                "firstname": "Dmitriy",
                "lastname": "Portsev",
                "paraclimbing_sport_class": null,
                "sport_class_status": null,
                "country": "RUS",
                "federation_id": 7,
                "rounds": []
            }
        ],
        "SPEED Women": [
            {
                "athlete_id": 42,
                "rank": 1,
                "firstname": "Tatiana",
                "lastname": "Ruyga",
                "paraclimbing_sport_class": null,
                "sport_class_status": null,
                "country": "RUS",
                "federation_id": 7,
                "rounds": []
            },
            {
                "athlete_id": 5731,
                "rank": 2,
                "firstname": "Yana",
                "lastname": "Malkova",
                "paraclimbing_sport_class": null,
                "sport_class_status": null,
                "country": "RUS",
                "federation_id": 7,
                "rounds": []
            },
            {
                "athlete_id": 45,
                "rank": 3,
                "firstname": "Valentina",
                "lastname": "Yurina",
                "paraclimbing_sport_class": null,
                "sport_class_status": null,
                "country": "RUS",
                "federation_id": 7,
                "rounds": []
            },
            {
                "athlete_id": 1468,
                "rank": 4,
                "firstname": "Olena",
                "lastname": "Ryepko",
                "paraclimbing_sport_class": null,
                "sport_class_status": null,
                "country": "UKR",
                "federation_id": 18,
                "rounds": []
            },
            {
                "athlete_id": 46,
                "rank": 5,
                "firstname": "Anna",
                "lastname": "Stenkovaya",
                "paraclimbing_sport_class": null,
                "sport_class_status": null,
                "country": "RUS",
                "federation_id": 7,
                "rounds": []
            },
            {
                "athlete_id": 4735,
                "rank": 6,
                "firstname": "Kseniia",
                "lastname": "Alekseeva",
                "paraclimbing_sport_class": null,
                "sport_class_status": null,
                "country": "RUS",
                "federation_id": 7,
                "rounds": []
            },
            {
                "athlete_id": 5110,
                "rank": 7,
                "firstname": "Olesya",
                "lastname": "Saulevich",
                "paraclimbing_sport_class": null,
                "sport_class_status": null,
                "country": "RUS",
                "federation_id": 7,
                "rounds": []
            },
            {
                "athlete_id": 1474,
                "rank": 8,
                "firstname": "Svitlana",
                "lastname": "Tuzhylina",
                "paraclimbing_sport_class": null,
                "sport_class_status": null,
                "country": "UKR",
                "federation_id": 18,
                "rounds": []
            },
            {
                "athlete_id": 50,
                "rank": 9,
                "firstname": "Tatiana",
                "lastname": "Shemulinkina ",
                "paraclimbing_sport_class": null,
                "sport_class_status": null,
                "country": "RUS",
                "federation_id": 7,
                "rounds": []
            },
            {
                "athlete_id": 58,
                "rank": 10,
                "firstname": "Yana",
                "lastname": "Chereshneva",
                "paraclimbing_sport_class": null,
                "sport_class_status": null,
                "country": "RUS",
                "federation_id": 7,
                "rounds": []
            },
            {
                "athlete_id": 4761,
                "rank": 11,
                "firstname": "Anna",
                "lastname": "Gallyamova",
                "paraclimbing_sport_class": null,
                "sport_class_status": null,
                "country": "RUS",
                "federation_id": 7,
                "rounds": []
            },
            {
                "athlete_id": 3176,
                "rank": 12,
                "firstname": "Francis",
                "lastname": "Rodriguez",
                "paraclimbing_sport_class": null,
                "sport_class_status": null,
                "country": "VEN",
                "federation_id": 42,
                "rounds": []
            },
            {
                "athlete_id": 5270,
                "rank": 13,
                "firstname": "Kristina",
                "lastname": "Nilsson",
                "paraclimbing_sport_class": null,
                "sport_class_status": null,
                "country": "SWE",
                "federation_id": 32,
                "rounds": []
            },
            {
                "athlete_id": 5735,
                "rank": 14,
                "firstname": "Lovise",
                "lastname": "Sparre",
                "paraclimbing_sport_class": null,
                "sport_class_status": null,
                "country": "SWE",
                "federation_id": 32,
                "rounds": []
            },
            {
                "athlete_id": 1482,
                "rank": 15,
                "firstname": "Nastasiya",
                "lastname": "Uvarova",
                "paraclimbing_sport_class": null,
                "sport_class_status": null,
                "country": "UKR",
                "federation_id": 18,
                "rounds": []
            }
        ]
    },
    "event_videos": [
        {
            "event_name": "BOULDER Men",
            "original_url": "",
            "ipfs_cid": ""
        },
        {
            "event_name": "BOULDER Women",
            "original_url": "",
            "ipfs_cid": ""
        },
        {
            "event_name": "SPEED Men",
            "original_url": "",
            "ipfs_cid": ""
        },
        {
            "event_name": "SPEED Women",
            "original_url": "",
            "ipfs_cid": ""
        }
    ]
}